Workbook

Sheet DATA
A1: Fecha | B1: Ruta | C1: Cliente | D1: Nombre | E1: Motivo No Entregado | F1: Unidad Negocio | G1: Responsable | H1: Eventos | I1: Cajas | J1: UNIDAD DE NEGOCIO FINAL | K1: LATITUD | L1: LONGITUD | M1: EMPRESARIO
A2: 46083 | B2: BK3712 | C2: 10200237 | D2: Carrillo Coll Cardenas, Benjamin Julio | E2: C9 NEN-Error carga | F2: Off Tradicional | G2: Logistic | H2: 1 | I2: 2 | J2: =VLOOKUP(C2,MAESTRO_CLIENTES!A:H,8,0) -> GIOVANY RUBINOS VILCHEZ | K2: =VLOOKUP(C2,MAESTRO_CLIENTES!A:Y,9,0) -> -12.03404 | L2: =VLOOKUP(C2,MAESTRO_CLIENTES!A:Y,10,0) -> -77.03095 | M2: =VLOOKUP(B2,Hoja1!B:C,2,0) -> SEGSOL S.A.C.
A3: 46083 | B3: BK3712 | C3: 11712811 | D3: Llampi, Juliana | E3: B4 NEN-Ausente | F3: Off Tradicional | G3: Customer | H3: 1 | I3: 4 | J3: =VLOOKUP(C3,MAESTRO_CLIENTES!A:H,8,0) -> GIOVANY RUBINOS VILCHEZ | K3: =VLOOKUP(C3,MAESTRO_CLIENTES!A:Y,9,0) -> -12.033006 | L3: =VLOOKUP(C3,MAESTRO_CLIENTES!A:Y,10,0) -> -77.029724 | M3: =VLOOKUP(B3,Hoja1!B:C,2,0) -> SEGSOL S.A.C.
A4: 46083 | B4: BK3712 | C4: 10932255 | D4: Mayorsa S.A. | E4: B8 NEN-Mal facturado | F4: Off Moderno | G4: Sales | H4: 1 | I4: 120 | J4: =VLOOKUP(C4,MAESTRO_CLIENTES!A:H,8,0) -> CHAVEZ HOLGUIN KENNER | K4: =VLOOKUP(C4,MAESTRO_CLIENTES!A:Y,9,0) -> -12.039674 | L4: =VLOOKUP(C4,MAESTRO_CLIENTES!A:Y,10,0) -> -77.032652 | M4: =VLOOKUP(B4,Hoja1!B:C,2,0) -> SEGSOL S.A.C.
A5: 46083 | B5: BK3712 | C5: 13942913 | D5: NECOCHEA FERNANDEZ, JOHAIRA JACKELIN | E5: C2 NEN-No ubicado | F5: Off Tradicional | G5: Sales | H5: 1 | I5: 3 | J5: =VLOOKUP(C5,MAESTRO_CLIENTES!A:H,8,0) -> GIOVANY RUBINOS VILCHEZ | K5: =VLOOKUP(C5,MAESTRO_CLIENTES!A:Y,9,0) -> -12.034149 | L5: =VLOOKUP(C5,MAESTRO_CLIENTES!A:Y,10,0) -> -77.028757 | M5: =VLOOKUP(B5,Hoja1!B:C,2,0) -> SEGSOL S.A.C.
A6: 46083 | B6: BK3712 | C6: 13327315 | D6: De La Cruz Masias, Alexander | E6: B4 NEN-Ausente | F6: On Tradicional | G6: Customer | H6: 2 | I6: 1.416666 | J6: =VLOOKUP(C6,MAESTRO_CLIENTES!A:H,8,0) -> ESTEBAN FERNANDEZ | K6: =VLOOKUP(C6,MAESTRO_CLIENTES!A:Y,9,0) -> -12.029749 | L6: =VLOOKUP(C6,MAESTRO_CLIENTES!A:Y,10,0) -> -77.030003 | M6: =VLOOKUP(B6,Hoja1!B:C,2,0) -> SEGSOL S.A.C.
A7: 46083 | B7: BK3712 | C7: 10236992 | D7: Pucuhuayla Solis, Gloria | E7: C9 NEN-Error carga | F7: Off Tradicional | G7: Logistic | H7: 1 | I7: 3 | J7: =VLOOKUP(C7,MAESTRO_CLIENTES!A:H,8,0) -> GIOVANY RUBINOS VILCHEZ | K7: =VLOOKUP(C7,MAESTRO_CLIENTES!A:Y,9,0) -> -12.033857 | L7: =VLOOKUP(C7,MAESTRO_CLIENTES!A:Y,10,0) -> -77.029907 | M7: =VLOOKUP(B7,Hoja1!B:C,2,0) -> SEGSOL S.A.C.
A8: 46083 | B8: BK3712 | C8: 12903380 | D8: Taipe Ortega, Bernardo | E8: B4 NEN-Ausente | F8: Off Tradicional | G8: Customer | H8: 1 | I8: 5 | J8: =VLOOKUP(C8,MAESTRO_CLIENTES!A:H,8,0) -> GIOVANY RUBINOS VILCHEZ | K8: =VLOOKUP(C8,MAESTRO_CLIENTES!A:Y,9,0) -> -12.03281 | L8: =VLOOKUP(C8,MAESTRO_CLIENTES!A:Y,10,0) -> -77.029673 | M8: =VLOOKUP(B8,Hoja1!B:C,2,0) -> SEGSOL S.A.C.
A9: 46083 | B9: BK3712 | C9: 13952187 | D9: Lilia Noelita Silva Villegas | E9: C9 NEN-Error carga | F9: Off Tradicional | G9: Logistic | H9: 1 | I9: 1 | J9: =VLOOKUP(C9,MAESTRO_CLIENTES!A:H,8,0) -> GIOVANY RUBINOS VILCHEZ | K9: =VLOOKUP(C9,MAESTRO_CLIENTES!A:Y,9,0) -> -12.029825 | L9: =VLOOKUP(C9,MAESTRO_CLIENTES!A:Y,10,0) -> -77.031842 | M9: =VLOOKUP(B9,Hoja1!B:C,2,0) -> SEGSOL S.A.C.
A10: 46083 | B10: BK3712 | C10: 14144216 | D10: RIOS DIONICIO, LUIS | E10: B3 NEN-Sin dinero | F10: Off Tradicional | G10: Customer | H10: 1 | I10: 4 | J10: =VLOOKUP(C10,MAESTRO_CLIENTES!A:H,8,0) -> GIOVANY RUBINOS VILCHEZ | K10: =VLOOKUP(C10,MAESTRO_CLIENTES!A:Y,9,0) -> -12.034322 | L10: =VLOOKUP(C10,MAESTRO_CLIENTES!A:Y,10,0) -> -77.039389 | M10: =VLOOKUP(B10,Hoja1!B:C,2,0) -> SEGSOL S.A.C.
A11: 46083 | B11: BK3760 | C11: 10262404 | D11: Supermercados Peruanos S.A. | E11: C1 NEN-Fuera de horario | F11: Off Moderno | G11: Logistic | H11: 2 | I11: 53 | J11: =VLOOKUP(C11,MAESTRO_CLIENTES!A:H,8,0) -> CHAVEZ HOLGUIN KENNER | K11: =VLOOKUP(C11,MAESTRO_CLIENTES!A:Y,9,0) -> -12.075344 | L11: =VLOOKUP(C11,MAESTRO_CLIENTES!A:Y,10,0) -> -77.053136 | M11: =VLOOKUP(B11,Hoja1!B:C,2,0) -> CORPORACION BREXIMAR S.A.C.
A12: 46083 | B12: BK3760 | C12: 11208713 | D12: Supermercados Peruanos S.A. | E12: C1 NEN-Fuera de horario | F12: Off Moderno | G12: Logistic | H12: 2 | I12: 78 | J12: =VLOOKUP(C12,MAESTRO_CLIENTES!A:H,8,0) -> CHAVEZ HOLGUIN KENNER | K12: =VLOOKUP(C12,MAESTRO_CLIENTES!A:Y,9,0) -> -12.065779 | L12: =VLOOKUP(C12,MAESTRO_CLIENTES!A:Y,10,0) -> -77.04831 | M12: =VLOOKUP(B12,Hoja1!B:C,2,0) -> CORPORACION BREXIMAR S.A.C.
A13: 46083 | B13: BK3760 | C13: 12174702 | D13: Palomino Rojas, Maria | E13: B3 NEN-Sin dinero | F13: Off Tradicional | G13: Customer | H13: 1 | I13: 1 | J13: =VLOOKUP(C13,MAESTRO_CLIENTES!A:H,8,0) -> HEIGER DONADONY CESPEDES CESPEDES | K13: =VLOOKUP(C13,MAESTRO_CLIENTES!A:Y,9,0) -> -12.067067 | L13: =VLOOKUP(C13,MAESTRO_CLIENTES!A:Y,10,0) -> -77.047023 | M13: =VLOOKUP(B13,Hoja1!B:C,2,0) -> CORPORACION BREXIMAR S.A.C.
... A167: 46084 | B167: BK3778 | C167: 13339689 | D167: Huatarunco Suclupe, Martin | E167: B8 NEN-Mal facturado | F167: Off Tradicional | G167: Sales | H167: 1 | I167: 11.25 | J167: =VLOOKUP(C167,MAESTRO_CLIENTES!A:H,8,0) -> DARCY JIMENEZ | K167: =VLOOKUP(C167,MAESTRO_CLIENTES!A:Y,9,0) -> -11.995579 | L167: =VLOOKUP(C167,MAESTRO_CLIENTES!A:Y,10,0) -> -77.004111 | M167: =VLOOKUP(B167,Hoja1!B:C,2,0) -> F & B ANDINA SAC
A168: 46084 | B168: BK3778 | C168: 13904865 | D168: #N/A | E168: C2 NEN-No ubicado | F168: #N/A | G168: Sales | H168: 1 | I168: 3 | J168: =VLOOKUP(C168,MAESTRO_CLIENTES!A:H,8,0) -> #N/A | K168: =VLOOKUP(C168,MAESTRO_CLIENTES!A:Y,9,0) -> #N/A | L168: =VLOOKUP(C168,MAESTRO_CLIENTES!A:Y,10,0) -> #N/A | M168: =VLOOKUP(B168,Hoja1!B:C,2,0) -> F & B ANDINA SAC
A169: 46084 | B169: BK3778 | C169: 14079060 | D169: Juan De Dios Canteno, Aurelio | E169: B6 NEN-No hizo pedido | F169: Off Tradicional | G169: Sales | H169: 1 | I169: 1 | J169: =VLOOKUP(C169,MAESTRO_CLIENTES!A:H,8,0) -> DARCY JIMENEZ | K169: =VLOOKUP(C169,MAESTRO_CLIENTES!A:Y,9,0) -> -11.998217 | L169: =VLOOKUP(C169,MAESTRO_CLIENTES!A:Y,10,0) -> -77.002956 | M169: =VLOOKUP(B169,Hoja1!B:C,2,0) -> F & B ANDINA SAC
A170: 46084 | B170: BK3778 | C170: 14226840 | D170: Nino De Guzman Navarro, Izumy Lourdes | E170: B1 NEN-Cerrado | F170: Off Tradicional | G170: Customer | H170: 1 | I170: 4 | J170: =VLOOKUP(C170,MAESTRO_CLIENTES!A:H,8,0) -> DARCY JIMENEZ | K170: =VLOOKUP(C170,MAESTRO_CLIENTES!A:Y,9,0) -> -12.005488 | L170: =VLOOKUP(C170,MAESTRO_CLIENTES!A:Y,10,0) -> -77.005337 | M170: =VLOOKUP(B170,Hoja1!B:C,2,0) -> F & B ANDINA SAC
A171: 46084 | B171: BK3722 | C171: 12754169 | D171: Zuniga Zapata, Alicia | E171: B1 NEN-Cerrado | F171: Off Tradicional | G171: Customer | H171: 1 | I171: 33 | J171: =VLOOKUP(C171,MAESTRO_CLIENTES!A:H,8,0) -> DARCY JIMENEZ | K171: =VLOOKUP(C171,MAESTRO_CLIENTES!A:Y,9,0) -> -12.033048 | L171: =VLOOKUP(C171,MAESTRO_CLIENTES!A:Y,10,0) -> -77.005672 | M171: =VLOOKUP(B171,Hoja1!B:C,2,0) -> JRGRODVAL DISTRIBUCIONES S.A.C.
A172: 46084 | B172: BK3722 | C172: 12886817 | D172: Perez Trauco, David Gonzalo | E172: C5 NEN-Atrib Camión o Ruta | F172: Off Tradicional | G172: Logistic | H172: 1 | I172: 1 | J172: =VLOOKUP(C172,MAESTRO_CLIENTES!A:H,8,0) -> DARCY JIMENEZ | K172: =VLOOKUP(C172,MAESTRO_CLIENTES!A:Y,9,0) -> -12.035869 | L172: =VLOOKUP(C172,MAESTRO_CLIENTES!A:Y,10,0) -> -77.005761 | M172: =VLOOKUP(B172,Hoja1!B:C,2,0) -> JRGRODVAL DISTRIBUCIONES S.A.C.
A173: 46084 | B173: BK3722 | C173: 12943386 | D173: ChacÃ³n Medina, Noris Luzmeri | E173: B1 NEN-Cerrado | F173: Off Tradicional | G173: Customer | H173: 1 | I173: 18 | J173: =VLOOKUP(C173,MAESTRO_CLIENTES!A:H,8,0) -> DARCY JIMENEZ | K173: =VLOOKUP(C173,MAESTRO_CLIENTES!A:Y,9,0) -> -12.040144 | L173: =VLOOKUP(C173,MAESTRO_CLIENTES!A:Y,10,0) -> -76.996205 | M173: =VLOOKUP(B173,Hoja1!B:C,2,0) -> JRGRODVAL DISTRIBUCIONES S.A.C.
A174: 46084 | B174: BK3764 | C174: 12112910 | D174: Eugenio Revilla, Melisa Dorelly | E174: B1 NEN-Cerrado | F174: Off Tradicional | G174: Customer | H174: 1 | I174: 6 | J174: =VLOOKUP(C174,MAESTRO_CLIENTES!A:H,8,0) -> DARCY JIMENEZ | K174: =VLOOKUP(C174,MAESTRO_CLIENTES!A:Y,9,0) -> -11.990313 | L174: =VLOOKUP(C174,MAESTRO_CLIENTES!A:Y,10,0) -> -77.003125 | M174: =VLOOKUP(B174,Hoja1!B:C,2,0) -> F & B ANDINA SAC
A175: 46084 | B175: BK3764 | C175: 12183159 | D175: Diaz Menacho, Mayra Melisaa | E175: B6 NEN-No hizo pedido | F175: Off Tradicional | G175: Sales | H175: 1 | I175: 25 | J175: =VLOOKUP(C175,MAESTRO_CLIENTES!A:H,8,0) -> DARCY JIMENEZ | K175: =VLOOKUP(C175,MAESTRO_CLIENTES!A:Y,9,0) -> -11.990924 | L175: =VLOOKUP(C175,MAESTRO_CLIENTES!A:Y,10,0) -> -77.000385 | M175: =VLOOKUP(B175,Hoja1!B:C,2,0) -> F & B ANDINA SAC
A176: 46084 | B176: BK3764 | C176: 12792178 | D176: Felix Choqueccahuana, Ynes | E176: B4 NEN-Ausente | F176: Off Tradicional | G176: Customer | H176: 2 | I176: 15.027778 | J176: =VLOOKUP(C176,MAESTRO_CLIENTES!A:H,8,0) -> DARCY JIMENEZ | K176: =VLOOKUP(C176,MAESTRO_CLIENTES!A:Y,9,0) -> -11.992052 | L176: =VLOOKUP(C176,MAESTRO_CLIENTES!A:Y,10,0) -> -77.009386 | M176: =VLOOKUP(B176,Hoja1!B:C,2,0) -> F & B ANDINA SAC
A177: 46084 | B177: BK3761 | C177: 14322960 | D177: Pastipiqueos Italianos S.A.C | E177: C9 NEN-Error carga | F177: On High End | G177: Logistic | H177: 2 | I177: 44 | J177: =VLOOKUP(C177,MAESTRO_CLIENTES!A:H,8,0) -> VALERIA KORN | K177: =VLOOKUP(C177,MAESTRO_CLIENTES!A:Y,9,0) -> -12.050221 | L177: =VLOOKUP(C177,MAESTRO_CLIENTES!A:Y,10,0) -> -77.041669 | M177: =VLOOKUP(B177,Hoja1!B:C,2,0) -> JRGRODVAL DISTRIBUCIONES S.A.C.
A178: 46084 | B178: BK3723 | C178: 11121178 | D178: Supermercados Peruanos S.A. | E178: B8 NEN-Mal facturado | F178: Off Moderno | G178: Sales | H178: 1 | I178: 19 | J178: =VLOOKUP(C178,MAESTRO_CLIENTES!A:H,8,0) -> CHAVEZ HOLGUIN KENNER | K178: =VLOOKUP(C178,MAESTRO_CLIENTES!A:Y,9,0) -> -12.028806 | L178: =VLOOKUP(C178,MAESTRO_CLIENTES!A:Y,10,0) -> -77.030928 | M178: =VLOOKUP(B178,Hoja1!B:C,2,0) -> CORPORACION BREXIMAR S.A.C.
A179: 46084 | B179: BK3723 | C179: 13434885 | D179: Rurush Tamara, Francisca | E179: B4 NEN-Ausente | F179: Off Tradicional | G179: Customer | H179: 1 | I179: 7.75 | J179: =VLOOKUP(C179,MAESTRO_CLIENTES!A:H,8,0) -> HEIGER DONADONY CESPEDES CESPEDES | K179: =VLOOKUP(C179,MAESTRO_CLIENTES!A:Y,9,0) -> -12.036133 | L179: =VLOOKUP(C179,MAESTRO_CLIENTES!A:Y,10,0) -> -77.046583 | M179: =VLOOKUP(B179,Hoja1!B:C,2,0) -> CORPORACION BREXIMAR S.A.C.
A180: 46084 | B180: BK3723 | C180: 14024371 | D180: LAPA ESPINOZA, VIRGEN | E180: B4 NEN-Ausente | F180: Off Tradicional | G180: Customer | H180: 1 | I180: 10 | J180: =VLOOKUP(C180,MAESTRO_CLIENTES!A:H,8,0) -> GIOVANY RUBINOS VILCHEZ | K180: =VLOOKUP(C180,MAESTRO_CLIENTES!A:Y,9,0) -> -12.023021 | L180: =VLOOKUP(C180,MAESTRO_CLIENTES!A:Y,10,0) -> -77.027912 | M180: =VLOOKUP(B180,Hoja1!B:C,2,0) -> CORPORACION BREXIMAR S.A.C.
... A222: 46084 | B222: BK3760 | C222: 14376695 | D222: Quillas Chumpitaz, Pedro Juan | E222: B8 NEN-Mal facturado | F222: Off Tradicional | G222: Sales | H222: 1 | I222: 2 | J222: =VLOOKUP(C222,MAESTRO_CLIENTES!A:H,8,0) -> HEIGER DONADONY CESPEDES CESPEDES | K222: =VLOOKUP(C222,MAESTRO_CLIENTES!A:Y,9,0) -> -12.067132 | L222: =VLOOKUP(C222,MAESTRO_CLIENTES!A:Y,10,0) -> -77.051382 | M222: =VLOOKUP(B222,Hoja1!B:C,2,0) -> CORPORACION BREXIMAR S.A.C.
A223: 46084 | B223: BK3760 | C223: 14466813 | D223: #N/A | E223: C4 NEN-Mala Calidad | F223: #N/A | G223: Logistic | H223: 1 | I223: 1 | J223: =VLOOKUP(C223,MAESTRO_CLIENTES!A:H,8,0) -> #N/A | K223: =VLOOKUP(C223,MAESTRO_CLIENTES!A:Y,9,0) -> #N/A | L223: =VLOOKUP(C223,MAESTRO_CLIENTES!A:Y,10,0) -> #N/A | M223: =VLOOKUP(B223,Hoja1!B:C,2,0) -> CORPORACION BREXIMAR S.A.C.
A224: 46084 | B224: BK3780 | C224: 13725692 | D224: CHAMBERGO MANRIQUE, JANETH MARITZA | E224: B8 NEN-Mal facturado | F224: On Tradicional | G224: Sales | H224: 1 | I224: 4 | J224: =VLOOKUP(C224,MAESTRO_CLIENTES!A:H,8,0) -> HEIGER DONADONY CESPEDES CESPEDES | K224: =VLOOKUP(C224,MAESTRO_CLIENTES!A:Y,9,0) -> -12.05143 | L224: =VLOOKUP(C224,MAESTRO_CLIENTES!A:Y,10,0) -> -77.029797 | M224: =VLOOKUP(B224,Hoja1!B:C,2,0) -> SEGSOL S.A.C.
A225: 46084 | B225: BK3780 | C225: 13799233 | D225: Flores Palomino, Noemi Amalia | E225: B8 NEN-Mal facturado | F225: Off Tradicional | G225: Sales | H225: 2 | I225: 1.999998 | J225: =VLOOKUP(C225,MAESTRO_CLIENTES!A:H,8,0) -> HEIGER DONADONY CESPEDES CESPEDES | K225: =VLOOKUP(C225,MAESTRO_CLIENTES!A:Y,9,0) -> -12.054837 | L225: =VLOOKUP(C225,MAESTRO_CLIENTES!A:Y,10,0) -> -77.037204 | M225: =VLOOKUP(B225,Hoja1!B:C,2,0) -> SEGSOL S.A.C.
A226: 46084 | B226: BK3780 | C226: 14373611 | D226: Tiendas Tambo S.A.C. | E226: B8 NEN-Mal facturado | F226: Off Moderno | G226: Sales | H226: 1 | I226: 8 | J226: =VLOOKUP(C226,MAESTRO_CLIENTES!A:H,8,0) -> CHAVEZ HOLGUIN KENNER | K226: =VLOOKUP(C226,MAESTRO_CLIENTES!A:Y,9,0) -> -12.05435 | L226: =VLOOKUP(C226,MAESTRO_CLIENTES!A:Y,10,0) -> -77.038974 | M226: =VLOOKUP(B226,Hoja1!B:C,2,0) -> SEGSOL S.A.C.
A227: 46084 | B227: BK3780 | C227: 14398201 | D227: Carrion Pezua, Yudith Vanesa | E227: C9 NEN-Error carga | F227: Off Tradicional | G227: Logistic | H227: 1 | I227: 1 | J227: =VLOOKUP(C227,MAESTRO_CLIENTES!A:H,8,0) -> HEIGER DONADONY CESPEDES CESPEDES | K227: =VLOOKUP(C227,MAESTRO_CLIENTES!A:Y,9,0) -> -12.05599 | L227: =VLOOKUP(C227,MAESTRO_CLIENTES!A:Y,10,0) -> -77.031724 | M227: =VLOOKUP(B227,Hoja1!B:C,2,0) -> SEGSOL S.A.C.
A228: 46084 | B228: BK3732 | C228: 13796236 | D228: Rosales Flores, Lucia Mariela | E228: B1 NEN-Cerrado | F228: Off Tradicional | G228: Customer | H228: 1 | I228: 12.225001 | J228: =VLOOKUP(C228,MAESTRO_CLIENTES!A:H,8,0) -> MIGUEL HERRERA | K228: =VLOOKUP(C228,MAESTRO_CLIENTES!A:Y,9,0) -> -11.965625 | L228: =VLOOKUP(C228,MAESTRO_CLIENTES!A:Y,10,0) -> -76.982416 | M228: =VLOOKUP(B228,Hoja1!B:C,2,0) -> F & B ANDINA SAC
A229: 46084 | B229: BK3732 | C229: 11649857 | D229: Ochoa Concepcion, Harumi | E229: C4 NEN-Mala Calidad | F229: Off Tradicional | G229: Logistic | H229: 1 | I229: 1 | J229: =VLOOKUP(C229,MAESTRO_CLIENTES!A:H,8,0) -> DARCY JIMENEZ | K229: =VLOOKUP(C229,MAESTRO_CLIENTES!A:Y,9,0) -> -11.97675 | L229: =VLOOKUP(C229,MAESTRO_CLIENTES!A:Y,10,0) -> -76.99819 | M229: =VLOOKUP(B229,Hoja1!B:C,2,0) -> F & B ANDINA SAC
A230: 46084 | B230: BK3732 | C230: 12497451 | D230: Giron Ramos, Guillermo | E230: C9 NEN-Error carga | F230: Off Tradicional | G230: Logistic | H230: 1 | I230: 1 | J230: =VLOOKUP(C230,MAESTRO_CLIENTES!A:H,8,0) -> DARCY JIMENEZ | K230: =VLOOKUP(C230,MAESTRO_CLIENTES!A:Y,9,0) -> -11.982785 | L230: =VLOOKUP(C230,MAESTRO_CLIENTES!A:Y,10,0) -> -76.99431 | M230: =VLOOKUP(B230,Hoja1!B:C,2,0) -> F & B ANDINA SAC
A231: 46084 | B231: BK3734 | C231: 10168403 | D231: Palomino Huallparimachi, Elvis | E231: B6 NEN-No hizo pedido | F231: Off Tradicional | G231: Sales | H231: 1 | I231: 6 | J231: =VLOOKUP(C231,MAESTRO_CLIENTES!A:H,8,0) -> HEIGER DONADONY CESPEDES CESPEDES | K231: =VLOOKUP(C231,MAESTRO_CLIENTES!A:Y,9,0) -> -12.076 | L231: =VLOOKUP(C231,MAESTRO_CLIENTES!A:Y,10,0) -> -77.05141 | M231: =VLOOKUP(B231,Hoja1!B:C,2,0) -> CORPORACION BREXIMAR S.A.C.
A232: 46084 | B232: BK3734 | C232: 12143474 | D232: Salcedo Casachagua, Edith Mariela | E232: B6 NEN-No hizo pedido | F232: Off Tradicional | G232: Sales | H232: 1 | I232: 2 | J232: =VLOOKUP(C232,MAESTRO_CLIENTES!A:H,8,0) -> HEIGER DONADONY CESPEDES CESPEDES | K232: =VLOOKUP(C232,MAESTRO_CLIENTES!A:Y,9,0) -> -12.076201 | L232: =VLOOKUP(C232,MAESTRO_CLIENTES!A:Y,10,0) -> -77.046884 | M232: =VLOOKUP(B232,Hoja1!B:C,2,0) -> CORPORACION BREXIMAR S.A.C.
A233: 46084 | B233: BK3734 | C233: 14435239 | D233: Luc Gud S.A.C. | E233: B1 NEN-Cerrado | F233: On Mid High End | G233: Customer | H233: 1 | I233: 4 | J233: =VLOOKUP(C233,MAESTRO_CLIENTES!A:H,8,0) -> ESTEBAN FERNANDEZ | K233: =VLOOKUP(C233,MAESTRO_CLIENTES!A:Y,9,0) -> -12.075299 | L233: =VLOOKUP(C233,MAESTRO_CLIENTES!A:Y,10,0) -> -77.044776 | M233: =VLOOKUP(B233,Hoja1!B:C,2,0) -> CORPORACION BREXIMAR S.A.C.
A234: 46084 | B234: BK3718 | C234: 14199686 | D234: Amaru Solis, David Javier | E234: C9 NEN-Error carga | F234: On Mid High End | G234: Logistic | H234: 3 | I234: 11.667261 | J234: =VLOOKUP(C234,MAESTRO_CLIENTES!A:H,8,0) -> ESTEBAN FERNANDEZ | K234: =VLOOKUP(C234,MAESTRO_CLIENTES!A:Y,9,0) -> -12.058946 | L234: =VLOOKUP(C234,MAESTRO_CLIENTES!A:Y,10,0) -> -77.03317 | M234: =VLOOKUP(B234,Hoja1!B:C,2,0) -> CORPORACION BREXIMAR S.A.C.
A235: 46084 | B235: BK3755 | C235: 12955363 | D235: Monsalve Alarcon, Gisella Elizabeth | E235: C4 NEN-Mala Calidad | F235: Off Tradicional | G235: Logistic | H235: 1 | I235: 1 | J235: =VLOOKUP(C235,MAESTRO_CLIENTES!A:H,8,0) -> DARCY JIMENEZ | K235: =VLOOKUP(C235,MAESTRO_CLIENTES!A:Y,9,0) -> -12.027201 | L235: =VLOOKUP(C235,MAESTRO_CLIENTES!A:Y,10,0) -> -77.02103 | M235: =VLOOKUP(B235,Hoja1!B:C,2,0) -> CORPORACION BREXIMAR S.A.C.
... A252: 46084 | B252: BK3769 | C252: 10772024 | D252: Cornejo De Alfaro, Ana Ruth | E252: B2 NEN-Sin envases | F252: Off Tradicional | G252: Customer | H252: 1 | I252: 1 | J252: =VLOOKUP(C252,MAESTRO_CLIENTES!A:H,8,0) -> DARCY JIMENEZ | K252: =VLOOKUP(C252,MAESTRO_CLIENTES!A:Y,9,0) -> -12.02669 | L252: =VLOOKUP(C252,MAESTRO_CLIENTES!A:Y,10,0) -> -77.01388 | M252: =VLOOKUP(B252,Hoja1!B:C,2,0) -> JRGRODVAL DISTRIBUCIONES S.A.C.
A253: 46084 | B253: BK3776 | C253: 12277733 | D253: #N/A | E253: C4 NEN-Mala Calidad | F253: #N/A | G253: Logistic | H253: 1 | I253: 1 | J253: =VLOOKUP(C253,MAESTRO_CLIENTES!A:H,8,0) -> #N/A | K253: =VLOOKUP(C253,MAESTRO_CLIENTES!A:Y,9,0) -> #N/A | L253: =VLOOKUP(C253,MAESTRO_CLIENTES!A:Y,10,0) -> #N/A | M253: =VLOOKUP(B253,Hoja1!B:C,2,0) -> F & B ANDINA SAC
A254: 46084 | B254: BK3765 | C254: 10195793 | D254: Urbano Villanueva, Cesar Augusto | E254: C4 NEN-Mala Calidad | F254: Off Tradicional | G254: Logistic | H254: 1 | I254: 1 | J254: =VLOOKUP(C254,MAESTRO_CLIENTES!A:H,8,0) -> DARCY JIMENEZ | K254: =VLOOKUP(C254,MAESTRO_CLIENTES!A:Y,9,0) -> -12.00453 | L254: =VLOOKUP(C254,MAESTRO_CLIENTES!A:Y,10,0) -> -76.996 | M254: =VLOOKUP(B254,Hoja1!B:C,2,0) -> CORPORACION BREXIMAR S.A.C.
A255: 46084 | B255: BK3747 | C255: 14021101 | D255: La alcoholeria de Magdalena S.A.C | E255: C9 NEN-Error carga | F255: Off Tradicional | G255: Logistic | H255: 1 | I255: 0.055556 | J255: =VLOOKUP(C255,MAESTRO_CLIENTES!A:H,8,0) -> HEIGER DONADONY CESPEDES CESPEDES | K255: =VLOOKUP(C255,MAESTRO_CLIENTES!A:Y,9,0) -> -12.091152 | L255: =VLOOKUP(C255,MAESTRO_CLIENTES!A:Y,10,0) -> -77.064665 | M255: =VLOOKUP(B255,Hoja1!B:C,2,0) -> CORPORACION BREXIMAR S.A.C.
A256: 46085 | B256: BK3715 | C256: 13478190 | D256: Santbru S.A.C | E256: B8 NEN-Mal facturado | F256: On High End | G256: Sales | H256: 1 | I256: 140 | J256: =VLOOKUP(C256,MAESTRO_CLIENTES!A:H,8,0) -> VALERIA KORN | K256: =VLOOKUP(C256,MAESTRO_CLIENTES!A:Y,9,0) -> -12.120293 | L256: =VLOOKUP(C256,MAESTRO_CLIENTES!A:Y,10,0) -> -77.032104 | M256: =VLOOKUP(B256,Hoja1!B:C,2,0) -> CORPORACION BREXIMAR S.A.C.
A257: 46085 | B257: BK3715 | C257: 14329672 | D257: INMOBILIARIA VISTAMAR S.A. | E257: B3 NEN-Sin dinero | F257: On High End | G257: Customer | H257: 1 | I257: 76 | J257: =VLOOKUP(C257,MAESTRO_CLIENTES!A:H,8,0) -> PAUL YOPLAC | K257: =VLOOKUP(C257,MAESTRO_CLIENTES!A:Y,9,0) -> -12.13294 | L257: =VLOOKUP(C257,MAESTRO_CLIENTES!A:Y,10,0) -> -77.02855 | M257: =VLOOKUP(B257,Hoja1!B:C,2,0) -> CORPORACION BREXIMAR S.A.C.
A258: 46085 | B258: BK3715 | C258: 13039158 | D258: Casa Noble Inversiones S.R.L. | E258: C4 NEN-Mala Calidad | F258: On High End | G258: Logistic | H258: 1 | I258: 1 | J258: =VLOOKUP(C258,MAESTRO_CLIENTES!A:H,8,0) -> ESTEBAN FERNANDEZ | K258: =VLOOKUP(C258,MAESTRO_CLIENTES!A:Y,9,0) -> -12.129375 | L258: =VLOOKUP(C258,MAESTRO_CLIENTES!A:Y,10,0) -> -77.032893 | M258: =VLOOKUP(B258,Hoja1!B:C,2,0) -> CORPORACION BREXIMAR S.A.C.
A259: 46085 | B259: BK3778 | C259: 10183330 | D259: Quispe Quispe, Ynes Pilar | E259: B8 NEN-Mal facturado | F259: Off Tradicional | G259: Sales | H259: 2 | I259: 54 | J259: =VLOOKUP(C259,MAESTRO_CLIENTES!A:H,8,0) -> GIOVANY RUBINOS VILCHEZ | K259: =VLOOKUP(C259,MAESTRO_CLIENTES!A:Y,9,0) -> -12.0343 | L259: =VLOOKUP(C259,MAESTRO_CLIENTES!A:Y,10,0) -> -77.03681 | M259: =VLOOKUP(B259,Hoja1!B:C,2,0) -> F & B ANDINA SAC
A260: 46085 | B260: BK3778 | C260: 12234337 | D260: Corporacion Vega S.A.C. | E260: C9 NEN-Error carga | F260: Off Moderno | G260: Logistic | H260: 1 | I260: 17 | J260: =VLOOKUP(C260,MAESTRO_CLIENTES!A:H,8,0) -> CHAVEZ HOLGUIN KENNER | K260: =VLOOKUP(C260,MAESTRO_CLIENTES!A:Y,9,0) -> -12.024513 | L260: =VLOOKUP(C260,MAESTRO_CLIENTES!A:Y,10,0) -> -77.029738 | M260: =VLOOKUP(B260,Hoja1!B:C,2,0) -> F & B ANDINA SAC
A261: 46085 | B261: BK3778 | C261: 13031263 | D261: Corporacion Rasel Asociados S.A.C. | E261: B3 NEN-Sin dinero | F261: Off Tradicional | G261: Customer | H261: 1 | I261: 8 | J261: =VLOOKUP(C261,MAESTRO_CLIENTES!A:H,8,0) -> GIOVANY RUBINOS VILCHEZ | K261: =VLOOKUP(C261,MAESTRO_CLIENTES!A:Y,9,0) -> -12.034395 | L261: =VLOOKUP(C261,MAESTRO_CLIENTES!A:Y,10,0) -> -77.038125 | M261: =VLOOKUP(B261,Hoja1!B:C,2,0) -> F & B ANDINA SAC
A262: 46085 | B262: BK3778 | C262: 13701603 | D262: TADEO MIGUEL, CRISTIAN OMAR | E262: B1 NEN-Cerrado | F262: Off Tradicional | G262: Customer | H262: 1 | I262: 38 | J262: =VLOOKUP(C262,MAESTRO_CLIENTES!A:H,8,0) -> GIOVANY RUBINOS VILCHEZ | K262: =VLOOKUP(C262,MAESTRO_CLIENTES!A:Y,9,0) -> -12.0348 | L262: =VLOOKUP(C262,MAESTRO_CLIENTES!A:Y,10,0) -> -77.040766 | M262: =VLOOKUP(B262,Hoja1!B:C,2,0) -> F & B ANDINA SAC
A263: 46085 | B263: BK3750 | C263: 10201935 | D263: Salazar Caja, Yanet Rosario | E263: B1 NEN-Cerrado | F263: Off Tradicional | G263: Customer | H263: 1 | I263: 10 | J263: =VLOOKUP(C263,MAESTRO_CLIENTES!A:H,8,0) -> GIOVANY RUBINOS VILCHEZ | K263: =VLOOKUP(C263,MAESTRO_CLIENTES!A:Y,9,0) -> -12.03207 | L263: =VLOOKUP(C263,MAESTRO_CLIENTES!A:Y,10,0) -> -77.0427 | M263: =VLOOKUP(B263,Hoja1!B:C,2,0) -> CORPORACION BREXIMAR S.A.C.
A264: 46085 | B264: BK3750 | C264: 11176846 | D264: MuÃ±oz Ricaldez, Daniel Eduardo | E264: B3 NEN-Sin dinero | F264: Off Tradicional | G264: Customer | H264: 1 | I264: 14.125 | J264: =VLOOKUP(C264,MAESTRO_CLIENTES!A:H,8,0) -> DARCY JIMENEZ | K264: =VLOOKUP(C264,MAESTRO_CLIENTES!A:Y,9,0) -> -11.977582 | L264: =VLOOKUP(C264,MAESTRO_CLIENTES!A:Y,10,0) -> -76.992785 | M264: =VLOOKUP(B264,Hoja1!B:C,2,0) -> CORPORACION BREXIMAR S.A.C.
A265: 46085 | B265: BK3750 | C265: 11690237 | D265: Neyra Rodriguez, Jaime Luis | E265: B1 NEN-Cerrado | F265: Off Tradicional | G265: Customer | H265: 1 | I265: 31 | J265: =VLOOKUP(C265,MAESTRO_CLIENTES!A:H,8,0) -> GIOVANY RUBINOS VILCHEZ | K265: =VLOOKUP(C265,MAESTRO_CLIENTES!A:Y,9,0) -> -12.029109 | L265: =VLOOKUP(C265,MAESTRO_CLIENTES!A:Y,10,0) -> -77.056713 | M265: =VLOOKUP(B265,Hoja1!B:C,2,0) -> CORPORACION BREXIMAR S.A.C.
... A285: 46085 | B285: BK3784 | C285: 13311890 | D285: Huaman Merino, Nazario | E285: B6 NEN-No hizo pedido | F285: On Tradicional | G285: Sales | H285: 1 | I285: 57 | J285: =VLOOKUP(C285,MAESTRO_CLIENTES!A:H,8,0) -> ESTEBAN FERNANDEZ | K285: =VLOOKUP(C285,MAESTRO_CLIENTES!A:Y,9,0) -> -12.06057 | L285: =VLOOKUP(C285,MAESTRO_CLIENTES!A:Y,10,0) -> -77.037951 | M285: =VLOOKUP(B285,Hoja1!B:C,2,0) -> JRGRODVAL DISTRIBUCIONES S.A.C.
A286: 46085 | B286: BK3784 | C286: 14463249 | D286: #N/A | E286: B1 NEN-Cerrado | F286: #N/A | G286: Customer | H286: 1 | I286: 15 | J286: =VLOOKUP(C286,MAESTRO_CLIENTES!A:H,8,0) -> #N/A | K286: =VLOOKUP(C286,MAESTRO_CLIENTES!A:Y,9,0) -> #N/A | L286: =VLOOKUP(C286,MAESTRO_CLIENTES!A:Y,10,0) -> #N/A | M286: =VLOOKUP(B286,Hoja1!B:C,2,0) -> JRGRODVAL DISTRIBUCIONES S.A.C.
A287: 46085 | B287: BK3775 | C287: 11511687 | D287: Destila2 S.A.C. | E287: B1 NEN-Cerrado | F287: Off Tradicional | G287: Customer | H287: 1 | I287: 27 | J287: =VLOOKUP(C287,MAESTRO_CLIENTES!A:H,8,0) -> HEIGER DONADONY CESPEDES CESPEDES | K287: =VLOOKUP(C287,MAESTRO_CLIENTES!A:Y,9,0) -> -11.944057 | L287: =VLOOKUP(C287,MAESTRO_CLIENTES!A:Y,10,0) -> -76.981511 | M287: =VLOOKUP(B287,Hoja1!B:C,2,0) -> JRGRODVAL DISTRIBUCIONES S.A.C.
A288: 46085 | B288: BK3775 | C288: 10190133 | D288: Huamani Galindo, Martina Lucia | E288: C9 NEN-Error carga | F288: Off Tradicional | G288: Logistic | H288: 1 | I288: 2 | J288: =VLOOKUP(C288,MAESTRO_CLIENTES!A:H,8,0) -> MIGUEL HERRERA | K288: =VLOOKUP(C288,MAESTRO_CLIENTES!A:Y,9,0) -> -11.94552 | L288: =VLOOKUP(C288,MAESTRO_CLIENTES!A:Y,10,0) -> -76.9861 | M288: =VLOOKUP(B288,Hoja1!B:C,2,0) -> JRGRODVAL DISTRIBUCIONES S.A.C.
A289: 46085 | B289: BK3775 | C289: 10190200 | D289: Molina Ccaccya De Alfaro, Victoria | E289: C9 NEN-Error carga | F289: Off Tradicional | G289: Logistic | H289: 1 | I289: 1 | J289: =VLOOKUP(C289,MAESTRO_CLIENTES!A:H,8,0) -> MIGUEL HERRERA | K289: =VLOOKUP(C289,MAESTRO_CLIENTES!A:Y,9,0) -> -11.94568 | L289: =VLOOKUP(C289,MAESTRO_CLIENTES!A:Y,10,0) -> -76.98641 | M289: =VLOOKUP(B289,Hoja1!B:C,2,0) -> JRGRODVAL DISTRIBUCIONES S.A.C.
A290: 46085 | B290: BK3775 | C290: 12283030 | D290: Choque Luna, Marina Luz | E290: C9 NEN-Error carga | F290: Off Tradicional | G290: Logistic | H290: 1 | I290: 1 | J290: =VLOOKUP(C290,MAESTRO_CLIENTES!A:H,8,0) -> MIGUEL HERRERA | K290: =VLOOKUP(C290,MAESTRO_CLIENTES!A:Y,9,0) -> -11.94538 | L290: =VLOOKUP(C290,MAESTRO_CLIENTES!A:Y,10,0) -> -76.984166 | M290: =VLOOKUP(B290,Hoja1!B:C,2,0) -> JRGRODVAL DISTRIBUCIONES S.A.C.
A291: 46085 | B291: BK3775 | C291: 12574031 | D291: Gutierrez Ortiz, Cyntia Bianca | E291: C9 NEN-Error carga | F291: On Tradicional | G291: Logistic | H291: 1 | I291: 5 | J291: =VLOOKUP(C291,MAESTRO_CLIENTES!A:H,8,0) -> ESTEBAN FERNANDEZ | K291: =VLOOKUP(C291,MAESTRO_CLIENTES!A:Y,9,0) -> -11.949 | L291: =VLOOKUP(C291,MAESTRO_CLIENTES!A:Y,10,0) -> -76.98561 | M291: =VLOOKUP(B291,Hoja1!B:C,2,0) -> JRGRODVAL DISTRIBUCIONES S.A.C.
A292: 46085 | B292: BK3775 | C292: 12709979 | D292: Canaza Nina, Yeni Karla | E292: B6 NEN-No hizo pedido | F292: Off Tradicional | G292: Sales | H292: 1 | I292: 5 | J292: =VLOOKUP(C292,MAESTRO_CLIENTES!A:H,8,0) -> MIGUEL HERRERA | K292: =VLOOKUP(C292,MAESTRO_CLIENTES!A:Y,9,0) -> -11.948143 | L292: =VLOOKUP(C292,MAESTRO_CLIENTES!A:Y,10,0) -> -76.984379 | M292: =VLOOKUP(B292,Hoja1!B:C,2,0) -> JRGRODVAL DISTRIBUCIONES S.A.C.
A293: 46085 | B293: BK3775 | C293: 12775391 | D293: Salinas Ochoa, Ricardo | E293: C9 NEN-Error carga | F293: Off Tradicional | G293: Logistic | H293: 1 | I293: 6 | J293: =VLOOKUP(C293,MAESTRO_CLIENTES!A:H,8,0) -> MIGUEL HERRERA | K293: =VLOOKUP(C293,MAESTRO_CLIENTES!A:Y,9,0) -> -11.94686 | L293: =VLOOKUP(C293,MAESTRO_CLIENTES!A:Y,10,0) -> -76.985381 | M293: =VLOOKUP(B293,Hoja1!B:C,2,0) -> JRGRODVAL DISTRIBUCIONES S.A.C.
A294: 46085 | B294: BK3775 | C294: 12923791 | D294: Huaman Condori, Marisol Milagros | E294: B6 NEN-No hizo pedido | F294: Off Tradicional | G294: Sales | H294: 1 | I294: 10 | J294: =VLOOKUP(C294,MAESTRO_CLIENTES!A:H,8,0) -> MIGUEL HERRERA | K294: =VLOOKUP(C294,MAESTRO_CLIENTES!A:Y,9,0) -> -11.948174 | L294: =VLOOKUP(C294,MAESTRO_CLIENTES!A:Y,10,0) -> -76.97606 | M294: =VLOOKUP(B294,Hoja1!B:C,2,0) -> JRGRODVAL DISTRIBUCIONES S.A.C.
A295: 46085 | B295: BK3775 | C295: 13968292 | D295: VASQUEZ ANTAYE, LAURA JESSICA | E295: B1 NEN-Cerrado | F295: Off Tradicional | G295: Customer | H295: 1 | I295: 2 | J295: =VLOOKUP(C295,MAESTRO_CLIENTES!A:H,8,0) -> MIGUEL HERRERA | K295: =VLOOKUP(C295,MAESTRO_CLIENTES!A:Y,9,0) -> -11.943564 | L295: =VLOOKUP(C295,MAESTRO_CLIENTES!A:Y,10,0) -> -76.986716 | M295: =VLOOKUP(B295,Hoja1!B:C,2,0) -> JRGRODVAL DISTRIBUCIONES S.A.C.
A296: 46085 | B296: BK3775 | C296: 14316176 | D296: BARRUETA CHUCO, LUCY | E296: B1 NEN-Cerrado | F296: Off Tradicional | G296: Customer | H296: 3 | I296: 11 | J296: =VLOOKUP(C296,MAESTRO_CLIENTES!A:H,8,0) -> MIGUEL HERRERA | K296: =VLOOKUP(C296,MAESTRO_CLIENTES!A:Y,9,0) -> -11.94491 | L296: =VLOOKUP(C296,MAESTRO_CLIENTES!A:Y,10,0) -> -76.98508 | M296: =VLOOKUP(B296,Hoja1!B:C,2,0) -> JRGRODVAL DISTRIBUCIONES S.A.C.
A297: 46085 | B297: BK3723 | C297: 11934536 | D297: Cevicheria Juancito S.A.C. | E297: B1 NEN-Cerrado | F297: On Tradicional | G297: Customer | H297: 1 | I297: 1 | J297: =VLOOKUP(C297,MAESTRO_CLIENTES!A:H,8,0) -> HEIGER DONADONY CESPEDES CESPEDES | K297: =VLOOKUP(C297,MAESTRO_CLIENTES!A:Y,9,0) -> -12.07899 | L297: =VLOOKUP(C297,MAESTRO_CLIENTES!A:Y,10,0) -> -77.05012 | M297: =VLOOKUP(B297,Hoja1!B:C,2,0) -> CORPORACION BREXIMAR S.A.C.
A298: 46085 | B298: BK3723 | C298: 12955978 | D298: Corporacion Vega S.A.C. | E298: C1 NEN-Fuera de horario | F298: Off Moderno | G298: Logistic | H298: 1 | I298: 8 | J298: =VLOOKUP(C298,MAESTRO_CLIENTES!A:H,8,0) -> CHAVEZ HOLGUIN KENNER | K298: =VLOOKUP(C298,MAESTRO_CLIENTES!A:Y,9,0) -> -12.077046 | L298: =VLOOKUP(C298,MAESTRO_CLIENTES!A:Y,10,0) -> -77.051489 | M298: =VLOOKUP(B298,Hoja1!B:C,2,0) -> CORPORACION BREXIMAR S.A.C.
... A410: 46086 | B410: BK3704 | C410: 12916964 | D410: Casallo Cerron, Norma | E410: B8 NEN-Mal facturado | F410: Off Tradicional | G410: Sales | H410: 1 | I410: 4 | J410: =VLOOKUP(C410,MAESTRO_CLIENTES!A:H,8,0) -> MIGUEL HERRERA | K410: =VLOOKUP(C410,MAESTRO_CLIENTES!A:Y,9,0) -> -11.944688 | L410: =VLOOKUP(C410,MAESTRO_CLIENTES!A:Y,10,0) -> -76.971189 | M410: =VLOOKUP(B410,Hoja1!B:C,2,0) -> CORPORACION BREXIMAR S.A.C.
A411: 46086 | B411: BK3704 | C411: 13905339 | D411: #N/A | E411: B6 NEN-No hizo pedido | F411: #N/A | G411: Sales | H411: 1 | I411: 1 | J411: =VLOOKUP(C411,MAESTRO_CLIENTES!A:H,8,0) -> #N/A | K411: =VLOOKUP(C411,MAESTRO_CLIENTES!A:Y,9,0) -> #N/A | L411: =VLOOKUP(C411,MAESTRO_CLIENTES!A:Y,10,0) -> #N/A | M411: =VLOOKUP(B411,Hoja1!B:C,2,0) -> CORPORACION BREXIMAR S.A.C.
A412: 46086 | B412: BK3704 | C412: 14144436 | D412: Rebaza Heredia, Jose Antonio | E412: B3 NEN-Sin dinero | F412: Off Tradicional | G412: Customer | H412: 1 | I412: 17 | J412: =VLOOKUP(C412,MAESTRO_CLIENTES!A:H,8,0) -> MIGUEL HERRERA | K412: =VLOOKUP(C412,MAESTRO_CLIENTES!A:Y,9,0) -> -11.941452 | L412: =VLOOKUP(C412,MAESTRO_CLIENTES!A:Y,10,0) -> -76.973915 | M412: =VLOOKUP(B412,Hoja1!B:C,2,0) -> CORPORACION BREXIMAR S.A.C.
A413: 46086 | B413: BK3704 | C413: 14177174 | D413: Nonalaya Rojas, Yadira Silvia | E413: B1 NEN-Cerrado | F413: Off Tradicional | G413: Customer | H413: 1 | I413: 21.499999 | J413: =VLOOKUP(C413,MAESTRO_CLIENTES!A:H,8,0) -> HEIGER DONADONY CESPEDES CESPEDES | K413: =VLOOKUP(C413,MAESTRO_CLIENTES!A:Y,9,0) -> -11.942758 | L413: =VLOOKUP(C413,MAESTRO_CLIENTES!A:Y,10,0) -> -76.972409 | M413: =VLOOKUP(B413,Hoja1!B:C,2,0) -> CORPORACION BREXIMAR S.A.C.
A414: 46086 | B414: BK3788 | C414: 14063241 | D414: Cadena De Comercio Peru S.A.C. | E414: B8 NEN-Mal facturado | F414: Off Moderno | G414: Sales | H414: 1 | I414: 1 | J414: =VLOOKUP(C414,MAESTRO_CLIENTES!A:H,8,0) -> CHAVEZ HOLGUIN KENNER | K414: =VLOOKUP(C414,MAESTRO_CLIENTES!A:Y,9,0) -> -11.947544 | L414: =VLOOKUP(C414,MAESTRO_CLIENTES!A:Y,10,0) -> -76.985229 | M414: =VLOOKUP(B414,Hoja1!B:C,2,0) -> JRGRODVAL DISTRIBUCIONES S.A.C.
A415: 46086 | B415: BK3788 | C415: 13778453 | D415: QUISPE PIRAN, RICHARD | E415: B1 NEN-Cerrado | F415: Off Tradicional | G415: Customer | H415: 2 | I415: 11 | J415: =VLOOKUP(C415,MAESTRO_CLIENTES!A:H,8,0) -> MIGUEL HERRERA | K415: =VLOOKUP(C415,MAESTRO_CLIENTES!A:Y,9,0) -> -11.946403 | L415: =VLOOKUP(C415,MAESTRO_CLIENTES!A:Y,10,0) -> -76.984615 | M415: =VLOOKUP(B415,Hoja1!B:C,2,0) -> JRGRODVAL DISTRIBUCIONES S.A.C.
A416: 46086 | B416: BK3788 | C416: 13203342 | D416: Rojas Escajadillo, Ara Ketty | E416: B1 NEN-Cerrado | F416: Off Tradicional | G416: Customer | H416: 1 | I416: 15 | J416: =VLOOKUP(C416,MAESTRO_CLIENTES!A:H,8,0) -> HEIGER DONADONY CESPEDES CESPEDES | K416: =VLOOKUP(C416,MAESTRO_CLIENTES!A:Y,9,0) -> -12.02424 | L416: =VLOOKUP(C416,MAESTRO_CLIENTES!A:Y,10,0) -> -77.026301 | M416: =VLOOKUP(B416,Hoja1!B:C,2,0) -> JRGRODVAL DISTRIBUCIONES S.A.C.
A417: 46086 | B417: BK3788 | C417: 10237439 | D417: Bustamante Tirado De Cusquillo, Dora Isab | E417: B1 NEN-Cerrado | F417: Off Tradicional | G417: Customer | H417: 1 | I417: 13 | J417: =VLOOKUP(C417,MAESTRO_CLIENTES!A:H,8,0) -> GIOVANY RUBINOS VILCHEZ | K417: =VLOOKUP(C417,MAESTRO_CLIENTES!A:Y,9,0) -> -12.02394 | L417: =VLOOKUP(C417,MAESTRO_CLIENTES!A:Y,10,0) -> -77.02982 | M417: =VLOOKUP(B417,Hoja1!B:C,2,0) -> JRGRODVAL DISTRIBUCIONES S.A.C.
A418: 46086 | B418: BK3788 | C418: 10189784 | D418: Pinto Gallegos, Mariano | E418: C4 NEN-Mala Calidad | F418: Off Tradicional | G418: Logistic | H418: 1 | I418: 1 | J418: =VLOOKUP(C418,MAESTRO_CLIENTES!A:H,8,0) -> MIGUEL HERRERA | K418: =VLOOKUP(C418,MAESTRO_CLIENTES!A:Y,9,0) -> -11.943192 | L418: =VLOOKUP(C418,MAESTRO_CLIENTES!A:Y,10,0) -> -76.984343 | M418: =VLOOKUP(B418,Hoja1!B:C,2,0) -> JRGRODVAL DISTRIBUCIONES S.A.C.
A419: 46086 | B419: BK3788 | C419: 11172171 | D419: Contreras Llamcce, Luis Alberto | E419: C4 NEN-Mala Calidad | F419: Off Tradicional | G419: Logistic | H419: 1 | I419: 1 | J419: =VLOOKUP(C419,MAESTRO_CLIENTES!A:H,8,0) -> GIOVANY RUBINOS VILCHEZ | K419: =VLOOKUP(C419,MAESTRO_CLIENTES!A:Y,9,0) -> -12.024817 | L419: =VLOOKUP(C419,MAESTRO_CLIENTES!A:Y,10,0) -> -77.028385 | M419: =VLOOKUP(B419,Hoja1!B:C,2,0) -> JRGRODVAL DISTRIBUCIONES S.A.C.
A420: 46086 | B420: BK3788 | C420: 11701964 | D420: Vargas Parodi, Feliciana | E420: B1 NEN-Cerrado | F420: Off Tradicional | G420: Customer | H420: 1 | I420: 17 | J420: =VLOOKUP(C420,MAESTRO_CLIENTES!A:H,8,0) -> MIGUEL HERRERA | K420: =VLOOKUP(C420,MAESTRO_CLIENTES!A:Y,9,0) -> -11.946462 | L420: =VLOOKUP(C420,MAESTRO_CLIENTES!A:Y,10,0) -> -76.991001 | M420: =VLOOKUP(B420,Hoja1!B:C,2,0) -> JRGRODVAL DISTRIBUCIONES S.A.C.
A421: 46086 | B421: BK3788 | C421: 14243434 | D421: Ramos Espinoza, Blanca Rosa | E421: B6 NEN-No hizo pedido | F421: Off Tradicional | G421: Sales | H421: 1 | I421: 10 | J421: =VLOOKUP(C421,MAESTRO_CLIENTES!A:H,8,0) -> MIGUEL HERRERA | K421: =VLOOKUP(C421,MAESTRO_CLIENTES!A:Y,9,0) -> -11.941193 | L421: =VLOOKUP(C421,MAESTRO_CLIENTES!A:Y,10,0) -> -76.994192 | M421: =VLOOKUP(B421,Hoja1!B:C,2,0) -> JRGRODVAL DISTRIBUCIONES S.A.C.
A422: 46086 | B422: BK3765 | C422: 11208713 | D422: Supermercados Peruanos S.A. | E422: C4 NEN-Mala Calidad | F422: Off Moderno | G422: Logistic | H422: 1 | I422: 3 | J422: =VLOOKUP(C422,MAESTRO_CLIENTES!A:H,8,0) -> CHAVEZ HOLGUIN KENNER | K422: =VLOOKUP(C422,MAESTRO_CLIENTES!A:Y,9,0) -> -12.065779 | L422: =VLOOKUP(C422,MAESTRO_CLIENTES!A:Y,10,0) -> -77.04831 | M422: =VLOOKUP(B422,Hoja1!B:C,2,0) -> CORPORACION BREXIMAR S.A.C.
A423: 46086 | B423: BK3765 | C423: 10262265 | D423: Supermercados Peruanos S.A. | E423: B4 NEN-Ausente | F423: Off Moderno | G423: Customer | H423: 2 | I423: 35 | J423: =VLOOKUP(C423,MAESTRO_CLIENTES!A:H,8,0) -> CHAVEZ HOLGUIN KENNER | K423: =VLOOKUP(C423,MAESTRO_CLIENTES!A:Y,9,0) -> -12.053967 | L423: =VLOOKUP(C423,MAESTRO_CLIENTES!A:Y,10,0) -> -77.043099 | M423: =VLOOKUP(B423,Hoja1!B:C,2,0) -> CORPORACION BREXIMAR S.A.C.
... A451: 46086 | B451: BK3705 | C451: 12809317 | D451: Jorge Calero, Elizabeth | E451: B6 NEN-No hizo pedido | F451: Off Tradicional | G451: Sales | H451: 1 | I451: 9 | J451: =VLOOKUP(C451,MAESTRO_CLIENTES!A:H,8,0) -> GIOVANY RUBINOS VILCHEZ | K451: =VLOOKUP(C451,MAESTRO_CLIENTES!A:Y,9,0) -> -12.025792 | L451: =VLOOKUP(C451,MAESTRO_CLIENTES!A:Y,10,0) -> -77.033403 | M451: =VLOOKUP(B451,Hoja1!B:C,2,0) -> CORPORACION BREXIMAR S.A.C.
A452: 46086 | B452: BK3705 | C452: 12928656 | D452: #N/A | E452: B4 NEN-Ausente | F452: #N/A | G452: Customer | H452: 1 | I452: 1.125 | J452: =VLOOKUP(C452,MAESTRO_CLIENTES!A:H,8,0) -> #N/A | K452: =VLOOKUP(C452,MAESTRO_CLIENTES!A:Y,9,0) -> #N/A | L452: =VLOOKUP(C452,MAESTRO_CLIENTES!A:Y,10,0) -> #N/A | M452: =VLOOKUP(B452,Hoja1!B:C,2,0) -> CORPORACION BREXIMAR S.A.C.
A453: 46086 | B453: BK3720 | C453: 10176088 | D453: Condor Diaz Vda De Herrera, Birginia | E453: B3 NEN-Sin dinero | F453: Off Tradicional | G453: Customer | H453: 1 | I453: 3 | J453: =VLOOKUP(C453,MAESTRO_CLIENTES!A:H,8,0) -> MIGUEL HERRERA | K453: =VLOOKUP(C453,MAESTRO_CLIENTES!A:Y,9,0) -> -11.96273 | L453: =VLOOKUP(C453,MAESTRO_CLIENTES!A:Y,10,0) -> -76.983303 | M453: =VLOOKUP(B453,Hoja1!B:C,2,0) -> CORPORACION BREXIMAR S.A.C.
A454: 46086 | B454: BK3720 | C454: 10950438 | D454: Miraval Leandro, Lida Edith | E454: B1 NEN-Cerrado | F454: Off Tradicional | G454: Customer | H454: 1 | I454: 4 | J454: =VLOOKUP(C454,MAESTRO_CLIENTES!A:H,8,0) -> MIGUEL HERRERA | K454: =VLOOKUP(C454,MAESTRO_CLIENTES!A:Y,9,0) -> -11.960952 | L454: =VLOOKUP(C454,MAESTRO_CLIENTES!A:Y,10,0) -> -76.987045 | M454: =VLOOKUP(B454,Hoja1!B:C,2,0) -> CORPORACION BREXIMAR S.A.C.
A455: 46086 | B455: BK3720 | C455: 12106369 | D455: De La O Olortegui, Norma Maribel | E455: B1 NEN-Cerrado | F455: Off Tradicional | G455: Customer | H455: 1 | I455: 12 | J455: =VLOOKUP(C455,MAESTRO_CLIENTES!A:H,8,0) -> MIGUEL HERRERA | K455: =VLOOKUP(C455,MAESTRO_CLIENTES!A:Y,9,0) -> -11.962172 | L455: =VLOOKUP(C455,MAESTRO_CLIENTES!A:Y,10,0) -> -76.986647 | M455: =VLOOKUP(B455,Hoja1!B:C,2,0) -> CORPORACION BREXIMAR S.A.C.
A456: 46086 | B456: BK3720 | C456: 12792507 | D456: Camacho Portillo, Jefferson Teofilo | E456: B1 NEN-Cerrado | F456: Off Tradicional | G456: Customer | H456: 1 | I456: 7 | J456: =VLOOKUP(C456,MAESTRO_CLIENTES!A:H,8,0) -> MIGUEL HERRERA | K456: =VLOOKUP(C456,MAESTRO_CLIENTES!A:Y,9,0) -> -11.959767 | L456: =VLOOKUP(C456,MAESTRO_CLIENTES!A:Y,10,0) -> -76.985787 | M456: =VLOOKUP(B456,Hoja1!B:C,2,0) -> CORPORACION BREXIMAR S.A.C.
A457: 46086 | B457: BK3720 | C457: 12811885 | D457: Arango Tuncar, Blanca Aurora | E457: C9 NEN-Error carga | F457: Off Tradicional | G457: Logistic | H457: 1 | I457: 6 | J457: =VLOOKUP(C457,MAESTRO_CLIENTES!A:H,8,0) -> MIGUEL HERRERA | K457: =VLOOKUP(C457,MAESTRO_CLIENTES!A:Y,9,0) -> -11.964711 | L457: =VLOOKUP(C457,MAESTRO_CLIENTES!A:Y,10,0) -> -76.969853 | M457: =VLOOKUP(B457,Hoja1!B:C,2,0) -> CORPORACION BREXIMAR S.A.C.
A458: 46086 | B458: BK3720 | C458: 12813848 | D458: Espinoza Huamani, Luis Enrique | E458: B1 NEN-Cerrado | F458: Off Tradicional | G458: Customer | H458: 1 | I458: 6 | J458: =VLOOKUP(C458,MAESTRO_CLIENTES!A:H,8,0) -> MIGUEL HERRERA | K458: =VLOOKUP(C458,MAESTRO_CLIENTES!A:Y,9,0) -> -11.959907 | L458: =VLOOKUP(C458,MAESTRO_CLIENTES!A:Y,10,0) -> -76.987339 | M458: =VLOOKUP(B458,Hoja1!B:C,2,0) -> CORPORACION BREXIMAR S.A.C.
A459: 46086 | B459: BK3720 | C459: 14331038 | D459: Villanueva Julca, Melissa Clara | E459: B3 NEN-Sin dinero | F459: Off Tradicional | G459: Customer | H459: 1 | I459: 1 | J459: =VLOOKUP(C459,MAESTRO_CLIENTES!A:H,8,0) -> MIGUEL HERRERA | K459: =VLOOKUP(C459,MAESTRO_CLIENTES!A:Y,9,0) -> -11.963863 | L459: =VLOOKUP(C459,MAESTRO_CLIENTES!A:Y,10,0) -> -76.981924 | M459: =VLOOKUP(B459,Hoja1!B:C,2,0) -> CORPORACION BREXIMAR S.A.C.
A460: 46086 | B460: BK3785 | C460: 13904546 | D460: BERROSPI TELADA,ALEX JOSMAR | E460: B8 NEN-Mal facturado | F460: Off Tradicional | G460: Sales | H460: 1 | I460: 36 | J460: =VLOOKUP(C460,MAESTRO_CLIENTES!A:H,8,0) -> HEIGER DONADONY CESPEDES CESPEDES | K460: =VLOOKUP(C460,MAESTRO_CLIENTES!A:Y,9,0) -> -12.043854 | L460: =VLOOKUP(C460,MAESTRO_CLIENTES!A:Y,10,0) -> -77.03563 | M460: =VLOOKUP(B460,Hoja1!B:C,2,0) -> SEGSOL S.A.C.
A461: 46086 | B461: BK3758 | C461: 12800087 | D461: LudeÃ±a Barbaran, Yoli | E461: C9 NEN-Error carga | F461: Off Tradicional | G461: Logistic | H461: 1 | I461: 1 | J461: =VLOOKUP(C461,MAESTRO_CLIENTES!A:H,8,0) -> DARCY JIMENEZ | K461: =VLOOKUP(C461,MAESTRO_CLIENTES!A:Y,9,0) -> -11.98012 | L461: =VLOOKUP(C461,MAESTRO_CLIENTES!A:Y,10,0) -> -76.98974 | M461: =VLOOKUP(B461,Hoja1!B:C,2,0) -> SEGSOL S.A.C.
A462: 46086 | B462: BK3758 | C462: 10195941 | D462: Marichi Amasifen, Berlith | E462: C9 NEN-Error carga | F462: Off Tradicional | G462: Logistic | H462: 1 | I462: 2 | J462: =VLOOKUP(C462,MAESTRO_CLIENTES!A:H,8,0) -> DARCY JIMENEZ | K462: =VLOOKUP(C462,MAESTRO_CLIENTES!A:Y,9,0) -> -11.977065 | L462: =VLOOKUP(C462,MAESTRO_CLIENTES!A:Y,10,0) -> -76.987417 | M462: =VLOOKUP(B462,Hoja1!B:C,2,0) -> SEGSOL S.A.C.
A463: 46086 | B463: BK3758 | C463: 11711999 | D463: Tapara Perez, Elena | E463: C5 NEN-Atrib Camión o Ruta | F463: Off Tradicional | G463: Logistic | H463: 1 | I463: 27 | J463: =VLOOKUP(C463,MAESTRO_CLIENTES!A:H,8,0) -> DARCY JIMENEZ | K463: =VLOOKUP(C463,MAESTRO_CLIENTES!A:Y,9,0) -> -11.976372 | L463: =VLOOKUP(C463,MAESTRO_CLIENTES!A:Y,10,0) -> -76.986706 | M463: =VLOOKUP(B463,Hoja1!B:C,2,0) -> SEGSOL S.A.C.
A464: 46086 | B464: BK3758 | C464: 14423393 | D464: AYALA CRUZ, NELLY | E464: B6 NEN-No hizo pedido | F464: Off Tradicional | G464: Sales | H464: 1 | I464: 1 | J464: =VLOOKUP(C464,MAESTRO_CLIENTES!A:H,8,0) -> DARCY JIMENEZ | K464: =VLOOKUP(C464,MAESTRO_CLIENTES!A:Y,9,0) -> -11.98949 | L464: =VLOOKUP(C464,MAESTRO_CLIENTES!A:Y,10,0) -> -76.99456 | M464: =VLOOKUP(B464,Hoja1!B:C,2,0) -> SEGSOL S.A.C.
... A466: 46086 | B466: BK3746 | C466: 12823989 | D466: Huamani Quispe, Susy | E466: B3 NEN-Sin dinero | F466: Off Tradicional | G466: Customer | H466: 1 | I466: 2 | J466: =VLOOKUP(C466,MAESTRO_CLIENTES!A:H,8,0) -> DARCY JIMENEZ | K466: =VLOOKUP(C466,MAESTRO_CLIENTES!A:Y,9,0) -> -12.007335 | L466: =VLOOKUP(C466,MAESTRO_CLIENTES!A:Y,10,0) -> -76.989236 | M466: =VLOOKUP(B466,Hoja1!B:C,2,0) -> CORPORACION BREXIMAR S.A.C.
A467: 46086 | B467: BK3746 | C467: 13916222 | D467: #N/A | E467: B1 NEN-Cerrado | F467: #N/A | G467: Customer | H467: 1 | I467: 17 | J467: =VLOOKUP(C467,MAESTRO_CLIENTES!A:H,8,0) -> #N/A | K467: =VLOOKUP(C467,MAESTRO_CLIENTES!A:Y,9,0) -> #N/A | L467: =VLOOKUP(C467,MAESTRO_CLIENTES!A:Y,10,0) -> #N/A | M467: =VLOOKUP(B467,Hoja1!B:C,2,0) -> CORPORACION BREXIMAR S.A.C.
A468: 46086 | B468: BK3750 | C468: 10237890 | D468: Condori Mamani De Mamani, Ignacia | E468: C9 NEN-Error carga | F468: Off Tradicional | G468: Logistic | H468: 1 | I468: 1 | J468: =VLOOKUP(C468,MAESTRO_CLIENTES!A:H,8,0) -> GIOVANY RUBINOS VILCHEZ | K468: =VLOOKUP(C468,MAESTRO_CLIENTES!A:Y,9,0) -> -12.016389 | L468: =VLOOKUP(C468,MAESTRO_CLIENTES!A:Y,10,0) -> -77.028566 | M468: =VLOOKUP(B468,Hoja1!B:C,2,0) -> CORPORACION BREXIMAR S.A.C.
...

Sheet Hoja1
A1: Fecha | B1: Ruta | C1: Empresario
A2: 46083 | B2: BK3712 | C2: SEGSOL S.A.C.
A3: 46083 | B3: BK3712 | C3: SEGSOL S.A.C.
A4: 46083 | B4: BK3712 | C4: SEGSOL S.A.C.
A5: 46083 | B5: BK3712 | C5: SEGSOL S.A.C.
A6: 46083 | B6: BK3712 | C6: SEGSOL S.A.C.
A7: 46083 | B7: BK3712 | C7: SEGSOL S.A.C.
A8: 46083 | B8: BK3712 | C8: SEGSOL S.A.C.
A9: 46083 | B9: BK3712 | C9: SEGSOL S.A.C.
A10: 46083 | B10: BK3712 | C10: SEGSOL S.A.C.
A11: 46083 | B11: BK3760 | C11: CORPORACION BREXIMAR S.A.C.
A12: 46083 | B12: BK3760 | C12: CORPORACION BREXIMAR S.A.C.
A13: 46083 | B13: BK3760 | C13: CORPORACION BREXIMAR S.A.C.
... A2166: 46098 | B2166: BK3755 | C2166: CORPORACION BREXIMAR S.A.C.

Sheet MAESTRO_CLIENTES
A1: cliente_id | B1: nombre | C1: direccion_geo | D1: distrito | E1: telefono | F1: canal | G1: zona_pem | H1: supervisor | I1: Latitud | J1: Longitud
A2: 10167450 | B2: Alvarado Delgado, Puol Jimmy | C2: Av. Arenales 2406 LINCE | D2: LINCE | E2: 980855740 | F2: Off Tradicional | G2: PEX578 | H2: HEIGER DONADONY CESPEDES CESPEDES | I2: -12.08826 | J2: -77.03513
A3: 10169835 | B3: Machuca Canales, Elsa | C3: Jr. Leticia 539 LIMA | D3: LIMA | E3: 978631416 | F3: Off Tradicional | G3: PEX525 | H3: HEIGER DONADONY CESPEDES CESPEDES | I3: -12.056713 | J3: -77.031164
A4: 10171859 | B4: Mejias Reyes, Lucy Clorinda | C4: Aa.hh. Ramon Carcamo Mz E3 Lt 1 LIMA | D4: LIMA | E4: 934887068 | F4: Off Tradicional | G4: PEX738 | H4: HEIGER DONADONY CESPEDES CESPEDES | I4: -12.042846 | J4: -77.050544
A5: 10172655 | B5: Libreria Bazar Amaya E.I.R.L. | C5: Av. EspaÃ±a 0487 LIMA | D5: LIMA | E5: 958340251 | F5: Off Tradicional | G5: PEMA28 | H5: HEIGER DONADONY CESPEDES CESPEDES | I5: -12.058265 | J5: -77.041321
A6: 10173198 | B6: Zelada Abanto, Severo Hermogenes | C6: Jr. Moquegua 0198 LIMA | D6: LIMA | E6: 990704643 | F6: On Tradicional | G6: PEX525 | H6: HEIGER DONADONY CESPEDES CESPEDES | I6: -12.04941 | J6: -77.034998
A7: 10177074 | B7: Sima Tinoco, Julio Ascencion | C7: Jr. Risso 0757 LINCE | D7: LINCE | E7: 949731304 | F7: Off Tradicional | G7: PEMA29 | H7: HEIGER DONADONY CESPEDES CESPEDES | I7: -12.084858 | J7: -77.028535
A8: 10178439 | B8: Olivas Trejo, Demetria Teodora | C8: Aa.hh. Perez De Cuellar Mz K-1 Lt 0 SAN JUAN DE LURIGANCHO | D8: SAN JUAN DE LURIGANCHO | E8: 923876940 | F8: Off Tradicional | G8: PEMA40 | H8: MIGUEL HERRERA | I8: -11.955465 | J8: -76.96919
A9: 10179265 | B9: Deudor De Pacheco, Epifania | C9: Jr. Perez De Tudela Mz F-17 Lt 010 SAN JUAN DE LURIGANCHO | D9: SAN JUAN DE LURIGANCHO | E9: 995925078 | F9: Off Tradicional | G9: PEX504 | H9: MIGUEL HERRERA | I9: -11.95236 | J9: -76.98421
A10: 10183416 | B10: Chirinos Mallqui, Sandra Karen | C10: Jr. Las Margaritas Mz T Lt 14 SAN JUAN DE LURIGANCHO | D10: SAN JUAN DE LURIGANCHO | E10: 990819522 | F10: Off Tradicional | G10: PEX523 | H10: DARCY JIMENEZ | I10: -12.00832 | J10: -76.98797
A11: 10184748 | B11: Rojas Huarcaya, Teodora | C11: Aa.hh. La Gruta Mz GU13 Lt 001 SAN JUAN DE LURIGANCHO | D11: SAN JUAN DE LURIGANCHO | E11: 948373684 | F11: Off Tradicional | G11: PEMA18 | H11: MIGUEL HERRERA | I11: -11.96641 | J11: -76.97517
A12: 10190255 | B12: Espinoza CastaÃ±eda, Noemi Demetria | C12: Conj.Hab. Cristo Rey Mz A Lt 28 SAN JUAN DE LURIGANCHO | D12: SAN JUAN DE LURIGANCHO | E12: 960746106 | F12: Off Tradicional | G12: PEMA40 | H12: MIGUEL HERRERA | I12: -11.939046 | J12: -77.009017
A13: 10191165 | B13: Rayme Rivas, Manuel Filiberto | C13: Coop. Sagrada Familia Mz A Lt 17 SAN JUAN DE LURIGANCHO | D13: SAN JUAN DE LURIGANCHO | E13: 013874666 | F13: Off Tradicional | G13: PEMA27 | H13: DARCY JIMENEZ | I13: -11.9762 | J13: -76.98774
A14: 10194648 | B14: Leon Zarate, Alcidas Rubila | C14: Jr. Los Robles 0421 SAN JUAN DE LURIGANCHO | D14: SAN JUAN DE LURIGANCHO | E14: 952380426 | F14: Off Tradicional | G14: PEX507 | H14: GIOVANY RUBINOS VILCHEZ | I14: -11.975028 | J14: -77.014133
A15: 10196293 | B15: Flores Garnique, Victoria | C15: Av. Canto Grande 2372 SAN JUAN DE LURIGANCHO | D15: SAN JUAN DE LURIGANCHO | E15: 01 2533792 | F15: Off Tradicional | G15: PEM745 | H15: SUPERVISOR PRUEBA | I15: -11.99089 | J15: -77.01507
A16: 10196517 | B16: Cardenas Guerrero, Juan De La Cruz | C16: Av. Los Ciruelos 435A SAN JUAN DE LURIGANCHO | D16: SAN JUAN DE LURIGANCHO | E16: 013876772 | F16: Off Tradicional | G16: PEMA10 | H16: DARCY JIMENEZ | I16: -11.98331 | J16: -77.005037
A17: 10196866 | B17: Hidalgo Pizarro, Rigoberto Samuel | C17: SV Villa Rosario Mz I Lt 5 SAN JUAN DE LURIGANCHO | D17: SAN JUAN DE LURIGANCHO | E17: 985620839 | F17: Off Tradicional | G17: PEMA17 | H17: DARCY JIMENEZ | I17: -11.999732 | J17: -76.995965
A18: 10196937 | B18: Sanchez Lozano, Lola Rosalbina | C18: Av. Clorinda Mattos Mz G1 Lt 6 SAN JUAN DE LURIGANCHO | D18: SAN JUAN DE LURIGANCHO | E18: 949244452 | F18: Off Tradicional | G18: PEMA55 | H18: GIOVANY RUBINOS VILCHEZ | I18: -11.96965 | J18: -77.00654
A19: 10199917 | B19: Veliz Vicharra, Teofilo Inocente | C19: Av. Los Tusilagos 0560 SAN JUAN DE LURIGANCHO | D19: SAN JUAN DE LURIGANCHO | E19: 014581441 | F19: Off Tradicional | G19: PEX522 | H19: DARCY JIMENEZ | I19: -12.012423 | J19: -77.010297
A20: 10200777 | B20: Cajo Rocha, Eulalia Margot | C20: Aa.hh. J.C.Mariategui Mz H3 Lt 35 SAN JUAN DE LURIGANCHO | D20: SAN JUAN DE LURIGANCHO | E20: 931323313 | F20: Off Tradicional | G20: PEMA18 | H20: MIGUEL HERRERA | I20: -11.943235 | J20: -76.983842
A21: 10201816 | B21: De La Cruz De Paucar, Rosaura | C21: Jr. San Juan De Pacheco Mz A Lt 008 SAN JUAN DE LURIGANCHO | D21: SAN JUAN DE LURIGANCHO | E21: 987636688 | F21: Off Tradicional | G21: PEX522 | H21: DARCY JIMENEZ | I21: -12.01907 | J21: -76.95501
A22: 10202779 | B22: Perez Tume, Claudio | C22: Jr. Los Amautas 1032 SAN JUAN DE LURIGANCHO | D22: SAN JUAN DE LURIGANCHO | E22: 991534386 | F22: Off Tradicional | G22: PEMA07 | H22: DARCY JIMENEZ | I22: -12.0251 | J22: -76.99615
A23: 10230347 | B23: Reyes Suarez, Minlly Vanessa | C23: Jr. Martin Olaya 941 SAN MARTIN DE PORRES | D23: SAN MARTIN DE PORRES | E23: 950104825 | F23: On Tradicional | G23: PEMA49 | H23: GIOVANY RUBINOS VILCHEZ | I23: -12.03138 | J23: -77.053862
A24: 10237367 | B24: Rubio Delgado, Jaime | C24: Ca. 14 0302 RIMAC | D24: RIMAC | E24: 986156970 | F24: Off Tradicional | G24: PEMA55 | H24: GIOVANY RUBINOS VILCHEZ | I24: -12.02564 | J24: -77.03139
A25: 10238519 | B25: Tello Lizarraga, Carlos Augusto | C25: Jr. Loreto 0594 RIMAC | D25: RIMAC | E25: 960602899 | F25: On Tradicional | G25: PEM159 | H25: ESTEBAN FERNANDEZ | I25: -12.042652 | J25: -77.024367
A26: 10580688 | B26: Jayo Villasana, Haydee Flora | C26: Ca. Ancash Mz C Lt 3 SAN JUAN DE LURIGANCHO | D26: SAN JUAN DE LURIGANCHO | E26: 922153038 | F26: Off Tradicional | G26: PEMA13 | H26: DARCY JIMENEZ | I26: -12.03248 | J26: -77.01422
A27: 10638822 | B27: Lima Lopez, Felix Rogelio | C27: Av. Jardines Este Mz C Lt 9 SAN JUAN DE LURIGANCHO | D27: SAN JUAN DE LURIGANCHO | E27: 934206377 | F27: Off Tradicional | G27: PEMA27 | H27: DARCY JIMENEZ | I27: -12.004262 | J27: -77.002738
A28: 10856119 | B28: Meza Flores, Percy Jesus | C28: Avenida progreso santa rosita mz 10 LIMA | D28: SAN JUAN DE LURIGANCHO | E28: 992732203 | F28: Off Tradicional | G28: PEMA13 | H28: DARCY JIMENEZ | I28: -12.03192 | J28: -77.01239
A29: 10931513 | B29: Lopez Sevillano, Viky | C29: Mz Dh Lt 9 Av Anchas Palomar SAN JUAN DE LURIGANCHO | D29: SAN JUAN DE LURIGANCHO | E29: 925071671 | F29: Off Tradicional | G29: PEMA37 | H29: MIGUEL HERRERA | I29: -11.918048 | J29: -76.953395
A30: 10981379 | B30: Restaurant Y Anticucheria La K-Ravana E.I.R.L. | C30: Av. Las Flores 190 SAN JUAN DE LURIGANCHO | D30: SAN JUAN DE LURIGANCHO | E30: 941711326 | F30: Off Tradicional | G30: PEX511 | H30: GIOVANY RUBINOS VILCHEZ | I30: -11.972501 | J30: -77.004134
A31: 11026090 | B31: Camacho Licona, Menelia | C31: Jr. Del Cruce Mz. O1 Lote 11 SAN JUAN DE LURIGANCHO | D31: SAN JUAN DE LURIGANCHO | E31: 946293039 | F31: Off Tradicional | G31: PEMA18 | H31: MIGUEL HERRERA | I31: -11.948768 | J31: -76.978828
A32: 11026601 | B32: Huaman Tapara, Delia Paulina | C32: Jr. Del Cerrito Mz. Q17 Lote 15 SAN JUAN DE LURIGANCHO | D32: SAN JUAN DE LURIGANCHO | E32: 977449768 | F32: Off Tradicional | G32: PEMA18 | H32: MIGUEL HERRERA | I32: -11.9385 | J32: -76.99353
A33: 11063836 | B33: Panta NiÃ±o De Infanzon, Yolanda | C33: Jr. Las Gravas 2065 SAN JUAN DE LURIGANCHO | D33: SAN JUAN DE LURIGANCHO | E33: 014597022 | F33: Off Tradicional | G33: PEMA10 | H33: DARCY JIMENEZ | I33: -11.997292 | J33: -77.007773
A34: 11135690 | B34: Silva Guevara, Manuel Jesus | C34: La Hoyada 188 RIMAC | D34: RIMAC | E34: 994374424 | F34: Off Tradicional | G34: PEMA55 | H34: GIOVANY RUBINOS VILCHEZ | I34: -12.026643 | J34: -77.031058
A35: 11177378 | B35: Cabrera Espinoza, Juana Liduvina | C35: Jr. Las Crisocalas 248 SAN JUAN DE LURIGANCHO | D35: SAN JUAN DE LURIGANCHO | E35: 956656209 | F35: Off Tradicional | G35: PEX523 | H35: DARCY JIMENEZ | I35: -11.986797 | J35: -77.005242
A36: 11195232 | B36: Inversiones Cusami E.I.R.L. | C36: Jiron Enrique Barron 1489 LINCE | D36: LIMA | E36: 990885803 | F36: Off Tradicional | G36: PEMA28 | H36: HEIGER DONADONY CESPEDES CESPEDES | I36: -12.078906 | J36: -77.032456
A37: 11453272 | B37: Sistemas Lurin S.A.C. | C37: Ca. Juan Figari 135 MIRAFLORES | D37: MIRAFLORES | E37: 939712061 | F37: Off Tradicional | G37: PEMA28 | H37: HEIGER DONADONY CESPEDES CESPEDES | I37: -12.122182 | J37: -77.031276
A38: 11592838 | B38: Terrazo Hinostroza, Kevin Aldahir | C38: Jr. Nevado Ausangate Mz A Lt 14 SAN JUAN DE LURIGANCHO | D38: SAN JUAN DE LURIGANCHO | E38: 946533217 | F38: Off Tradicional | G38: PEX509 | H38: GIOVANY RUBINOS VILCHEZ | I38: -11.98294 | J38: -77.01414
A39: 11650033 | B39: Veramendi Silvestre, Anabel Fabiola | C39: Ca. 5 Mz B Lt 28 SAN JUAN DE LURIGANCHO | D39: SAN JUAN DE LURIGANCHO | E39: 901403069 | F39: Off Tradicional | G39: PEMA27 | H39: DARCY JIMENEZ | I39: -12.019643 | J39: -76.967072
A40: 11750847 | B40: Cardenas Valdivieso, Roman Anthony | C40: Ca. Algarrobos Mz A Lt 27 EL AGUSTINO | D40: EL AGUSTINO | E40: 915156480 | F40: On Tradicional | G40: PEM159 | H40: ESTEBAN FERNANDEZ | I40: -12.039303 | J40: -76.995902
A41: 11802385 | B41: Fernandez Pedraza, Dilfredo | C41: Jr. Bambas 498 LIMA | D41: LIMA | E41: 930616146 | F41: Off Tradicional | G41: PEX525 | H41: HEIGER DONADONY CESPEDES CESPEDES | I41: -12.055504 | J41: -77.032234
A42: 12119572 | B42: Gonzales Fuentes De Cosio, Juana Delia | C42: Pj. San Lucas Mz B Lt 02 SAN JUAN DE LURIGANCHO | D42: SAN JUAN DE LURIGANCHO | E42: 902438502 | F42: Off Tradicional | G42: PEMA08 | H42: DARCY JIMENEZ | I42: -12.01776 | J42: -77.004526
A43: 12163456 | B43: Canasa Perez, Eudocia | C43: Aa.hh. Villa El Trebol Anexo 22 Mz SAN JUAN DE LURIGANCHO | D43: SAN JUAN DE LURIGANCHO | E43: 932436726 | F43: Off Tradicional | G43: PEMA44 | H43: MIGUEL HERRERA | I43: -11.898978 | J43: -76.967811
A44: 12189160 | B44: Mendoza Ramos, Violeta Mabelsa | C44: Av. Venezuela 1750A BREÃ‘A | D44: BREÃ‘A | E44: 918503242 | F44: Off Tradicional | G44: PEX126 | H44: HEIGER DONADONY CESPEDES CESPEDES | I44: -12.05562 | J44: -77.05658
A45: 12201881 | B45: Huaman Huaman, Arturo | C45: Residen. Martinete Mz A Lt 05 LIMA | D45: LIMA | E45: 993403007 | F45: Off Tradicional | G45: PEX524 | H45: HEIGER DONADONY CESPEDES CESPEDES | I45: -12.042666 | J45: -77.0137
... A69: 13228023 | B69: Ortega Antaurco, Nick Jerson | C69: Psj el altillo interior 2 MZ a LT 7 RIMAC | D69: RIMAC | E69: 927374992 | F69: On Tradicional | G69: PEMA45 | H69: GIOVANY RUBINOS VILCHEZ | I69: -12.020086 | J69: -77.027969
A70: 13248738 | B70: PÃ©rez Menor, Jose | C70: Jiron las galletas 539 MZ a SAN JUAN DE LURIGANCHO | D70: SAN JUAN DE LURIGANCHO | E70: 001681444 | F70: Off Tradicional | G70: PEMA08 | H70: DARCY JIMENEZ | I70: -12.001234 | J70: -77.002053
A71: 13315213 | B71: Meza Doza, Judith Angelina | C71: Asentamiento Humano Los Jazmines Mz SAN JUAN DE LURIGANCHO | D71: SAN JUAN DE LURIGANCHO | E71: 912288188 | F71: Off Tradicional | G71: PEMA09 | H71: DARCY JIMENEZ | I71: -12.013127 | J71: -76.9898
A72: 13316724 | B72: Palomino Cusi, Veronica | C72: Jiron JosÃ© GÃ¡lvez 1546 LINCE | D72: LINCE | E72: 977469892 | F72: Off Tradicional | G72: PEMA28 | H72: HEIGER DONADONY CESPEDES CESPEDES | I72: -12.079422 | J72: -77.029852
A73: 13320790 | B73: Ãngulo Carranza, Sheila Judith | C73: Jiron Manuel Vargas 113 RIMAC | D73: RIMAC | E73: 960890459 | F73: Off Tradicional | G73: PEX507 | H73: GIOVANY RUBINOS VILCHEZ | I73: -12.025646 | J73: -77.025703
A74: 13323283 | B74: Ayala RodrÃ­guez, Luis Arnulfo | C74: Jr Camana 337 LIMA | D74: LIMA | E74: 993694101 | F74: On Tradicional | G74: PEM159 | H74: ESTEBAN FERNANDEZ | I74: -12.045829 | J74: -77.032889
A75: 13326401 | B75: Rocca Gonzales, Juan De Dio | C75: Av Huaynacapac Mz Bc7 Lt 3A SAN JUAN DE LURIGANCHO | D75: SAN JUAN DE LURIGANCHO | E75: 938591473 | F75: Off Tradicional | G75: PEX500 | H75: MIGUEL HERRERA | I75: -11.932522 | J75: -76.944226
A76: 13364169 | B76: Araujo Zavala, Edith Rosa | C76: Jiron Cajamarca 596 RIMAC | D76: RIMAC | E76: 990535181 | F76: Off Tradicional | G76: PEMA45 | H76: GIOVANY RUBINOS VILCHEZ | I76: -12.040452 | J76: -77.02285
A77: 13448559 | B77: RodrÃ­guez Trillo, Gulliana Josselyn | C77: Avenida NicolÃ¡s De Pierola 781 LIMA | D77: LIMA | E77: 999242818 | F77: Off Tradicional | G77: PEX525 | H77: HEIGER DONADONY CESPEDES CESPEDES | I77: -12.05069 | J77: -77.036402
A78: 13479551 | B78: Michue Rojas, Cindy | C78: Jr Zamora 159 LIMA | D78: LIMA | E78: 934610258 | F78: Off Tradicional | G78: PEX526 | H78: HEIGER DONADONY CESPEDES CESPEDES | I78: -12.045786 | J78: -77.043698
A79: 13896578 | B79: GUTIERREZ QUINTANA,LUIS ALEJANDRO | C79: JIRON ANCASH 1074 LIMA | D79: LIMA | E79: 993141644 | F79: Off Tradicional | G79: PEX524 | H79: HEIGER DONADONY CESPEDES CESPEDES | I79: -12.047295 | J79: -77.018841
A80: 13949778 | B80: FLORES ARGUELLES, SMITH JHONATAN | C80: JIRON JUAN PABLO II 2 SAN JUAN DE LURIGANCHO | D80: SAN JUAN DE LURIGANCHO | E80: 961163906 | F80: Off Tradicional | G80: PEMA17 | H80: DARCY JIMENEZ | I80: -11.98707 | J80: -76.97521
A81: 13995168 | B81: QUISPE GAVIDIA, KEVIN FREDY | C81: Avenida Petit Thouars 4553 MIRAFLORES | D81: MIRAFLORES | E81: 967040369 | F81: Off Tradicional | G81: PEMA29 | H81: HEIGER DONADONY CESPEDES CESPEDES | I81: -12.107966 | J81: -77.029584
A82: 14000940 | B82: ROMISONCCO PEREZ HERNAN | C82: cruce entre Av Salaverry cdra 6 con JESUS MARIA | D82: JESUS MARIA | E82: 967092775 | F82: Off Tradicional | G82: PEMA29 | H82: HEIGER DONADONY CESPEDES CESPEDES | I82: -12.07134 | J82: -77.041286
... A97: 14380389 | B97: Condori Llacho, Magdalena | C97: Calle Huancho Mz by8 lote 18 Jicama SAN JUAN DE LURIGANCHO | D97: SAN JUAN DE LURIGANCHO | E97: 936973237 | F97: Off Tradicional | G97: PEMA44 | H97: MIGUEL HERRERA | I97: -11.909877 | J97: -76.973765
A98: 14451105 | B98: SIFUENTES ZAVALA VDA DE NAVARRO, OLIMPIA | C98: Aaahh union progreso 14 de febrero LURIGANCHO | D98: SAN JUAN DE LURIGANCHO | F98: Off Tradicional | G98: PEMA37 | H98: MIGUEL HERRERA | I98: -11.940982 | J98: -76.962053
A99: 10173165 | B99: Contreras Solari, Delia Irene | C99: Jr. Ancash 0240 LIMA | D99: LIMA | F99: Off Tradicional | G99: PEX526 | H99: HEIGER DONADONY CESPEDES CESPEDES | I99: -12.044997 | J99: -77.028615
A100: 10175307 | B100: Mercantil Alimenticia San Pedro E.I.R.L. | C100: Aa.hh. Mariscal Caceres Mz L18 Lt 1 SAN JUAN DE LURIGANCHO | D100: SAN JUAN DE LURIGANCHO | F100: Off Tradicional | G100: PEMA40 | H100: MIGUEL HERRERA | I100: -11.951575 | J100: -76.980445
A101: 10192849 | B101: Lozano Espejo, Yolanda Isabel | C101: Urb. Mariscal Caceres Mz K5 Lt 02 SAN JUAN DE LURIGANCHO | D101: SAN JUAN DE LURIGANCHO | F101: Off Tradicional | G101: PEX504 | H101: MIGUEL HERRERA | I101: -11.95075 | J101: -76.98221
A102: 10195404 | B102: Macedo De Lopez, Felicita V | C102: Jr. Amelos 2125 SAN JUAN DE LURIGANCHO | D102: SAN JUAN DE LURIGANCHO | F102: Off Tradicional | G102: PEMA08 | H102: DARCY JIMENEZ | I102: -11.99814 | J102: -77.01397
A103: 10195994 | B103: Sanchez Elguera, Epifanio | C103: Jr. Artesanos Mz D2 Lt 9 SAN JUAN DE LURIGANCHO | D103: SAN JUAN DE LURIGANCHO | F103: Off Tradicional | G103: PEX504 | H103: MIGUEL HERRERA | I103: -11.96695 | J103: -76.99135
A104: 10197880 | B104: De La Cruz Gonzales, Eufemia Maria | C104: Psje. Ovalo Amancaes Mz D Lt 30A SAN JUAN DE LURIGANCHO | D104: SAN JUAN DE LURIGANCHO | F104: Off Tradicional | G104: PEX507 | H104: GIOVANY RUBINOS VILCHEZ | I104: -11.97509 | J104: -77.01613
A105: 10198873 | B105: Mego Mendoza, Nena | C105: L.viol 2a Mz C Lt 3 SAN JUAN DE LURIGANCHO | D105: SAN JUAN DE LURIGANCHO | F105: On Tradicional | G105: PEMA12 | H105: DARCY JIMENEZ | I105: -12.011995 | J105: -77.007641
A106: 10202945 | B106: Asto Urbano De Garcia, Celia | C106: Av. Lima 0192 SAN JUAN DE LURIGANCHO | D106: SAN JUAN DE LURIGANCHO | F106: Off Tradicional | G106: PEMA07 | H106: DARCY JIMENEZ | I106: -12.02542 | J106: -77.01335
A107: 10210111 | B107: Hipolito Marin De Mendoza, Nelly | C107: Ca. Los Descalzos 0112 RIMAC | D107: RIMAC | F107: Off Tradicional | G107: PEX506 | H107: GIOVANY RUBINOS VILCHEZ | I107: -12.035451 | J107: -77.024995
A108: 10238221 | B108: Sumi Valera, Fidel | C108: Aa.hh. Juan Pablo Ii Mz C Lt 003 RIMAC | D108: RIMAC | F108: Off Tradicional | G108: PEMA53 | H108: GIOVANY RUBINOS VILCHEZ | I108: -12.01283 | J108: -77.02947
A109: 10238668 | B109: Moreno LiÃ±an, Rosa Alejandra | C109: Ca. 12 Mz S Lt 006 RIMAC | D109: RIMAC | F109: Off Tradicional | G109: PEX506 | H109: GIOVANY RUBINOS VILCHEZ | I109: -12.03624 | J109: -77.02216
... A2008: 14413463 | B2008: Cadena De Comercio Peru S.A.C. | C2008: Calle AlfredoÂ SalazarÂ N 298 Miraflo Miraflores | D2008: MIRAFLORES | F2008: Off Moderno | G2008: PEM225 | H2008: AMAYA CORTAVITARTE JULIO BRAULIO | I2008: -12.109845 | J2008: -77.03884
A2009: 14414905 | B2009: Soto Pena, Vilma Eulalia | C2009: MZ A lt 32 Los jardines SAN JUAN DE MIRAFLORES | F2009: Off Tradicional | G2009: PEX738 | H2009: HEIGER DONADONY CESPEDES CESPEDES | I2009: -12.7605 | J2009: -76.975359
A2010: 14449642 | B2010: CONCESIONES DEL PACIFICO S.A.C. | C2010: M3Circuito de playas Costa Verde 47 Miraflores | D2010: MIRAFLORES | F2010: On High End | G2010: PEM400 | H2010: VALERIA KORN | I2010: -12.127655 | J2010: -77.037243
A2011: 10166134 | B2011: Castro Carbajal, Jeannelt | C2011: Jr. Moquegua 676 LIMA | D2011: LIMA | F2011: On Tradicional | G2011: PEX526 | H2011: HEIGER DONADONY CESPEDES CESPEDES | I2011: -12.046288 | J2011: -77.039855
A2012: 10166986 | B2012: Trinidad Vivas, Gladys Giannina | C2012: Jr. Conchucos 893 LIMA | D2012: LIMA | F2012: Off Tradicional | G2012: PEX524 | H2012: HEIGER DONADONY CESPEDES CESPEDES | I2012: -12.05143 | J2012: -77.01169
A2013: 10172606 | B2013: Onofre Quispe De Inga, Alejandra | C2013: Calle Huallaga Mz 142-A Lt 18 SAN JUAN DE LURIGANCHO | D2013: SAN JUAN DE LURIGANCHO | F2013: Off Tradicional | G2013: PEX511 | H2013: GIOVANY RUBINOS VILCHEZ | I2013: -11.96461 | J2013: -77.01406
A2014: 10174483 | B2014: Cutimanco Soto, Carmen Rosa | C2014: Av. Las Magnolias 0281 EL AGUSTINO | D2014: EL AGUSTINO | F2014: Off Tradicional | G2014: PEX512 | H2014: DARCY JIMENEZ | I2014: -12.03562 | J2014: -77.00568
A2015: 10174708 | B2015: Vargas Rosas, Jose Luis | C2015: Aa.hh. Bayovar Mz 46 Lt 6 SAN JUAN DE LURIGANCHO | D2015: SAN JUAN DE LURIGANCHO | F2015: Off Tradicional | G2015: PEMA22 | H2015: MIGUEL HERRERA | I2015: -11.950582 | J2015: -76.995763
A2016: 10176928 | B2016: Ore LudeÃ±a, Gloria | C2016: Jr. Platinos 570 Mz E1 Lt 016 SAN JUAN DE LURIGANCHO | D2016: SAN JUAN DE LURIGANCHO | F2016: On Tradicional | G2016: PEM415 | H2016: ESTEBAN FERNANDEZ | I2016: -11.99517 | J2016: -77.00321
A2017: 10177258 | B2017: Quezada Zavaleta De Jave, Blanca Paquin | C2017: Aa.hh. Santa Maria Mz G3 Lt 006 SAN JUAN DE LURIGANCHO | D2017: SAN JUAN DE LURIGANCHO | F2017: Off Tradicional | G2017: PEMA42 | H2017: MIGUEL HERRERA | I2017: -11.96378 | J2017: -76.96871
A2018: 10178697 | B2018: Perez Cerdan, Luz Aurora | C2018: Aa.hh. 10 De Octubre Mz A15 Lt 046 SAN JUAN DE LURIGANCHO | D2018: SAN JUAN DE LURIGANCHO | F2018: Off Tradicional | G2018: PEMA42 | H2018: MIGUEL HERRERA | I2018: -11.94747 | J2018: -76.98577
A2019: 10179245 | B2019: Sandoval Castillo, Martha Elena | C2019: Jr. Los Chasquis 351 SAN JUAN DE LURIGANCHO | D2019: SAN JUAN DE LURIGANCHO | F2019: Off Tradicional | G2019: PEMA27 | H2019: DARCY JIMENEZ | I2019: -12.026303 | J2019: -77.009693
A2020: 10179989 | B2020: Huapaya Garcia, Gloria Bertha | C2020: Sotomayor Pimentel 234 Int. 14 LIMA | D2020: LIMA | F2020: Off Tradicional | G2020: PEX524 | H2020: HEIGER DONADONY CESPEDES CESPEDES | I2020: -12.05432 | J2020: -77.016433
A2021: 10188061 | B2021: Pinto , Paula Rebeca | C2021: Aa.hh. Huascar Mz 148 Lt 022 SAN JUAN DE LURIGANCHO | D2021: SAN JUAN DE LURIGANCHO | F2021: Off Tradicional | G2021: PEMA67 | H2021: GIOVANY RUBINOS VILCHEZ | I2021: -11.96852 | J2021: -77.01062
... A2314: 14444664 | B2314: Cadena De Comercio Peru S.A.C. | C2314: General Ãlvarez de Arenales 1387 CERCADO | D2314: LIMA | F2314: Off Moderno | G2314: PEM221 | H2314: ALVARADO MONTALVO CHRISTIAN JHONATA | I2314: -12.078378 | J2314: -77.036376
A2315: 14447016 | B2315: El Arte Del Catering E.I.R.L. | C2315: PANAMERICANA SUR KM 92.5 ASIA | F2315: On Mid High End | G2315: PEX021 | H2315: RODRIGO HERNANDEZ | I2315: -12.743945 | J2315: 76.632183
A2316: 14448220 | B2316: ALCANTARA CUBA, RAQUEL | C2316: Urb Compradores MZ N Lt 10 LURIGANCHO | D2316: SAN JUAN DE LURIGANCHO | F2316: Off Tradicional | G2316: PEMA10 | H2316: DARCY JIMENEZ | I2316: -12.015017 | J2316: -76.962665
A2317: 10181921 | B2317: Minaya Gallardo, Julian | C2317: Jr. Las Bellotitas 0703 SAN JUAN DE LURIGANCHO | D2317: SAN JUAN DE LURIGANCHO | F2317: Off Tradicional | G2317: PEMA27 | H2317: DARCY JIMENEZ | I2317: -12.017426 | J2317: -77.009746
A2318: 10182556 | B2318: Cabello Paucar, Nicolasa | C2318: Urb. Los Huertos De Canto Grande Mz SAN JUAN DE LURIGANCHO | D2318: SAN JUAN DE LURIGANCHO | F2318: Off Tradicional | G2318: PEMA37 | H2318: MIGUEL HERRERA | I2318: -11.943795 | J2318: -76.964393
A2319: 10185423 | B2319: Villanueva Magallanes De Amable, Carmen Rosa | C2319: Aa.hh. 15 De Enero Mz Ã‘ Lt 003 SAN JUAN DE LURIGANCHO | D2319: SAN JUAN DE LURIGANCHO | F2319: Off Tradicional | G2319: PEMA53 | H2319: GIOVANY RUBINOS VILCHEZ | I2319: -12.009457 | J2319: -77.015954
A2320: 10189810 | B2320: Aquino Davila, Dimas Cristina | C2320: Mz X5 Lt 24, AmpliaciÃƒÂ³n Mariategui SAN JUAN DE LURIGANCHO | D2320: SAN JUAN DE LURIGANCHO | F2320: Off Tradicional | G2320: PEMA42 | H2320: MIGUEL HERRERA | I2320: -11.930933 | J2320: -76.991345
A2321: 10191797 | B2321: Carrion Echevarria, Aide Esperanza | C2321: Aa.hh. Huascar Gpo 07 Mz 71 Lt 003 SAN JUAN DE LURIGANCHO | D2321: SAN JUAN DE LURIGANCHO | F2321: Off Tradicional | G2321: PEMA49 | H2321: GIOVANY RUBINOS VILCHEZ | I2321: -11.96235 | J2321: -77.007125
A2322: 10192329 | B2322: Alejandro Alejo, Evarista | C2322: Aa.hh. Huascar Gpo 05 Mz 120 Lt 18 SAN JUAN DE LURIGANCHO | D2322: SAN JUAN DE LURIGANCHO | F2322: Off Tradicional | G2322: PEMA53 | H2322: GIOVANY RUBINOS VILCHEZ | I2322: -11.96451 | J2322: -77.00949
A2323: 10193434 | B2323: Hilario Perez De Quiroz, Prisca Liberata | C2323: Av. San Martin De Porres Este 311 SAN JUAN DE LURIGANCHO | D2323: SAN JUAN DE LURIGANCHO | F2323: Off Tradicional | G2323: PEMA51 | H2323: GIOVANY RUBINOS VILCHEZ | I2323: -11.97018 | J2323: -76.998317
A2324: 10194833 | B2324: Zegarra Rojas Vda De Garcia, Lidovinda | C2324: Aa.hh. E.Montenegro Mz R1 Lt 28 SAN JUAN DE LURIGANCHO | D2324: SAN JUAN DE LURIGANCHO | F2324: On Mid High End | G2324: PEM415 | H2324: ESTEBAN FERNANDEZ | I2324: -11.93599 | J2324: -76.9724
A2325: 10195360 | B2325: Rodriguez Dionisio, Rosa Elvira | C2325: Jr. Nebulosas 2679 SAN JUAN DE LURIGANCHO | D2325: SAN JUAN DE LURIGANCHO | F2325: Off Tradicional | G2325: PEMA51 | H2325: GIOVANY RUBINOS VILCHEZ | I2325: -11.986225 | J2325: -77.008508
A2326: 10195988 | B2326: Huamani Inca, Redy | C2326: Aa.hh. J.C.Mariategui Mz S1 Lt 24 SAN JUAN DE LURIGANCHO | D2326: SAN JUAN DE LURIGANCHO | F2326: Off Tradicional | G2326: PEMA41 | H2326: MIGUEL HERRERA | I2326: -11.935103 | J2326: -76.989398
A2327: 10200806 | B2327: Pacco Gallegos, Guellermina | C2327: Urb. Ciudad Mcal.Caceres Mz F Lt 24 SAN JUAN DE LURIGANCHO | D2327: SAN JUAN DE LURIGANCHO | F2327: Off Tradicional | G2327: PEMA18 | H2327: MIGUEL HERRERA | I2327: -11.949025 | J2327: -76.976465
...
